{
  "sim_id": "kiln_ceramic_runbook",
  "state": {
    "sim_id": "kiln_ceramic_runbook",
    "current_time_hours": 95.0,
    "inventory": {
      "labor_bot_general_v0": {
        "quantity": 2.0,
        "unit": "unit"
      },
      "assembly_station": {
        "quantity": 1.0,
        "unit": "unit"
      },
      "assembly_tools_basic": {
        "quantity": 1.0,
        "unit": "unit"
      },
      "refractory_installation_tools": {
        "quantity": 1.0,
        "unit": "unit"
      },
      "mixer_or_blender": {
        "quantity": 1.0,
        "unit": "unit"
      },
      "chemical_reactor_basic": {
        "quantity": 1.0,
        "unit": "unit"
      },
      "alumina_powder": {
        "quantity": 1.0,
        "unit": "kg"
      },
      "processed_tailings_v0": {
        "quantity": 294.0,
        "unit": "kg"
      },
      "kiln_ceramic": {
        "quantity": 1.0,
        "unit": "unit"
      }
    },
    "active_processes": [],
    "machines_built": [],
    "machines_in_use": {},
    "total_imports": {
      "labor_bot_general_v0": {
        "quantity": 2.0,
        "unit": "unit"
      },
      "assembly_station": {
        "quantity": 1.0,
        "unit": "unit"
      },
      "assembly_tools_basic": {
        "quantity": 1.0,
        "unit": "unit"
      },
      "refractory_installation_tools": {
        "quantity": 1.0,
        "unit": "unit"
      },
      "mixer_or_blender": {
        "quantity": 1.0,
        "unit": "unit"
      },
      "chemical_reactor_basic": {
        "quantity": 1.0,
        "unit": "unit"
      },
      "hydrochloric_acid": {
        "quantity": 30.0,
        "unit": "kg"
      },
      "ceramic_binder": {
        "quantity": 10.0,
        "unit": "kg"
      },
      "water": {
        "quantity": 5.0,
        "unit": "kg"
      },
      "heating_element_resistive": {
        "quantity": 2.0,
        "unit": "kg"
      },
      "electrical_wire_and_connectors": {
        "quantity": 2.0,
        "unit": "kg"
      },
      "control_circuit_board_basic": {
        "quantity": 1.0,
        "unit": "unit"
      }
    },
    "provenance": {
      "labor_bot_general_v0": {
        "in_situ_kg": 0.0,
        "imported_kg": 240.0,
        "unknown_kg": 0.0
      },
      "assembly_station": {
        "in_situ_kg": 0.0,
        "imported_kg": 80.0,
        "unknown_kg": 0.0
      },
      "assembly_tools_basic": {
        "in_situ_kg": 0.0,
        "imported_kg": 50.0,
        "unknown_kg": 0.0
      },
      "refractory_installation_tools": {
        "in_situ_kg": 0.0,
        "imported_kg": 10.0,
        "unknown_kg": 0.0
      },
      "mixer_or_blender": {
        "in_situ_kg": 0.0,
        "imported_kg": 80.0,
        "unknown_kg": 0.0
      },
      "chemical_reactor_basic": {
        "in_situ_kg": 0.0,
        "imported_kg": 500.0,
        "unknown_kg": 0.0
      },
      "regolith_lunar_highlands": {
        "in_situ_kg": 0.0,
        "imported_kg": 0.0,
        "unknown_kg": 0.0
      },
      "hydrochloric_acid": {
        "in_situ_kg": 0.0,
        "imported_kg": 0.0,
        "unknown_kg": 0.0
      },
      "alumina_powder": {
        "in_situ_kg": 0.9090909090909101,
        "imported_kg": 0.09090909090909083,
        "unknown_kg": 0.0
      },
      "processed_tailings_v0": {
        "in_situ_kg": 267.27272727272725,
        "imported_kg": 26.727272727272727,
        "unknown_kg": 0.0
      },
      "ceramic_binder": {
        "in_situ_kg": 0.0,
        "imported_kg": 0.0,
        "unknown_kg": 0.0
      },
      "water": {
        "in_situ_kg": 0.0,
        "imported_kg": 0.0,
        "unknown_kg": 0.0
      },
      "refractory_castable": {
        "in_situ_kg": 0.0,
        "imported_kg": 0.0,
        "unknown_kg": 0.0
      },
      "heating_element_resistive": {
        "in_situ_kg": 0.0,
        "imported_kg": 0.0,
        "unknown_kg": 0.0
      },
      "electrical_wire_and_connectors": {
        "in_situ_kg": 0.0,
        "imported_kg": 0.0,
        "unknown_kg": 0.0
      },
      "control_circuit_board_basic": {
        "in_situ_kg": 0.0,
        "imported_kg": 0.0,
        "unknown_kg": 0.0
      },
      "furnace_chamber_unequipped": {
        "in_situ_kg": 31.18181818181818,
        "imported_kg": 17.818181818181817,
        "unknown_kg": 0.0
      },
      "furnace_chamber_equipped": {
        "in_situ_kg": 0.42424242424242425,
        "imported_kg": 1.575757575757576,
        "unknown_kg": 0.0
      },
      "kiln_ceramic": {
        "in_situ_kg": 0.2121212121212121,
        "imported_kg": 4.787878787878788,
        "unknown_kg": 0.0
      }
    },
    "complexity_scores": {
      "regolith_lunar_highlands": 1,
      "alumina_powder": 2,
      "processed_tailings_v0": 2,
      "refractory_castable": 3,
      "furnace_chamber_unequipped": 4,
      "furnace_chamber_equipped": 5,
      "kiln_ceramic": 6
    },
    "total_energy_kwh": 173.29999999999998
  },
  "scheduler": {
    "current_time": 95.0,
    "event_queue": [],
    "active_processes": {},
    "completed_processes": [
      {
        "process_run_id": "cef62adf-3ee2-478b-b61a-b76d4ee82269",
        "process_id": "regolith_mining_lunar_highlands_v0",
        "start_time": 0.0,
        "duration_hours": 3.0,
        "end_time": 3.0,
        "scale": 1.0,
        "inputs_consumed": {},
        "outputs_pending": {
          "regolith_lunar_highlands": 300.0
        },
        "outputs_pending_units": {
          "regolith_lunar_highlands": "kg"
        },
        "machines_reserved": {
          "labor_bot_general_v0": 1.0
        },
        "provenance_consumed_kg": {
          "in_situ_kg": 0.0,
          "imported_kg": 0.0,
          "unknown_kg": 0.0
        },
        "inputs_consumed_units": {},
        "recipe_run_id": "bfa7dd3c-a293-4a29-aaba-8a4aca96d994",
        "step_index": 0,
        "energy_kwh": 15.0
      },
      {
        "process_run_id": "4d4bded7-20a3-404a-953e-c44e89609ac1",
        "process_id": "alumina_extraction_from_highlands_v0",
        "start_time": 5.0,
        "duration_hours": 30.0,
        "end_time": 35.0,
        "scale": 1.0,
        "inputs_consumed": {
          "regolith_lunar_highlands": 300.0,
          "hydrochloric_acid": 30.0
        },
        "outputs_pending": {
          "alumina_powder": 36.0,
          "processed_tailings_v0": 294.0
        },
        "outputs_pending_units": {
          "alumina_powder": "kg",
          "processed_tailings_v0": "kg"
        },
        "machines_reserved": {
          "chemical_reactor_basic": 1.0,
          "labor_bot_general_v0": 1.0
        },
        "provenance_consumed_kg": {
          "in_situ_kg": 300.0,
          "imported_kg": 30.0,
          "unknown_kg": 0.0
        },
        "inputs_consumed_units": {
          "regolith_lunar_highlands": "kg",
          "hydrochloric_acid": "kg"
        },
        "recipe_run_id": "3aa8f7fe-6d9f-4394-9762-663a935ddcbc",
        "step_index": 0,
        "energy_kwh": 108.0
      },
      {
        "process_run_id": "09a35046-6e5b-47e2-afb5-b3606a88d22d",
        "process_id": "refractory_castable_mixing_v0",
        "start_time": 45.0,
        "duration_hours": 25.0,
        "end_time": 70.0,
        "scale": 1.0,
        "inputs_consumed": {
          "alumina_powder": 35.0,
          "ceramic_binder": 10.0,
          "water": 5.0
        },
        "outputs_pending": {
          "refractory_castable": 50.0
        },
        "outputs_pending_units": {
          "refractory_castable": "kg"
        },
        "machines_reserved": {
          "labor_bot_general_v0": 1.0,
          "mixer_or_blender": 1.0
        },
        "provenance_consumed_kg": {
          "in_situ_kg": 31.818181818181817,
          "imported_kg": 18.18181818181818,
          "unknown_kg": 0.0
        },
        "inputs_consumed_units": {
          "alumina_powder": "kg",
          "ceramic_binder": "kg",
          "water": "kg"
        },
        "recipe_run_id": "c0e69cbe-8be1-4aca-b36e-b61aa569ab90",
        "step_index": 0,
        "energy_kwh": 10.0
      },
      {
        "process_run_id": "93eaed36-4ec1-43b2-aac4-68ee2cbf95d0",
        "process_id": "refractory_casting_v0",
        "start_time": 75.0,
        "duration_hours": 1.0,
        "end_time": 76.0,
        "scale": 1.0,
        "inputs_consumed": {
          "refractory_castable": 50.0
        },
        "outputs_pending": {
          "furnace_chamber_unequipped": 1.0
        },
        "outputs_pending_units": {
          "furnace_chamber_unequipped": "unit"
        },
        "machines_reserved": {
          "labor_bot_general_v0": 1.0,
          "refractory_installation_tools": 1.0
        },
        "provenance_consumed_kg": {
          "in_situ_kg": 31.818181818181817,
          "imported_kg": 18.18181818181818,
          "unknown_kg": 0.0
        },
        "inputs_consumed_units": {
          "refractory_castable": "kg"
        },
        "recipe_run_id": "d497a1c7-20cb-45b1-911c-16169f5637a8",
        "step_index": 0,
        "energy_kwh": 40.0
      },
      {
        "process_run_id": "ce6fad8c-50cf-47c2-b25e-3409572f2cc1",
        "process_id": "heating_element_installation_v0",
        "start_time": 76.0,
        "duration_hours": 1.0,
        "end_time": 77.0,
        "scale": 1.0,
        "inputs_consumed": {
          "heating_element_resistive": 1.0,
          "furnace_chamber_unequipped": 1.0
        },
        "outputs_pending": {
          "furnace_chamber_equipped": 1.0
        },
        "outputs_pending_units": {
          "furnace_chamber_equipped": "unit"
        },
        "machines_reserved": {
          "labor_bot_general_v0": 1.0,
          "assembly_tools_basic": 1.0
        },
        "provenance_consumed_kg": {
          "in_situ_kg": 0.6363636363636364,
          "imported_kg": 2.3636363636363638,
          "unknown_kg": 0.0
        },
        "inputs_consumed_units": {
          "heating_element_resistive": "unit",
          "furnace_chamber_unequipped": "unit"
        },
        "recipe_run_id": "d497a1c7-20cb-45b1-911c-16169f5637a8",
        "step_index": 1,
        "energy_kwh": 0.1
      },
      {
        "process_run_id": "12d9a378-567a-4f8d-9019-4b2817954749",
        "process_id": "electrical_assembly_basic_v0",
        "start_time": 77.0,
        "duration_hours": 1.0,
        "end_time": 78.0,
        "scale": 1.0,
        "inputs_consumed": {
          "furnace_chamber_equipped": 1.0,
          "electrical_wire_and_connectors": 2.0,
          "control_circuit_board_basic": 1.0
        },
        "outputs_pending": {
          "kiln_ceramic": 1.0
        },
        "outputs_pending_units": {
          "kiln_ceramic": "unit"
        },
        "machines_reserved": {
          "labor_bot_general_v0": 1.0,
          "assembly_tools_basic": 1.0
        },
        "provenance_consumed_kg": {
          "in_situ_kg": 0.2121212121212121,
          "imported_kg": 4.787878787878788,
          "unknown_kg": 0.0
        },
        "inputs_consumed_units": {
          "furnace_chamber_equipped": "unit",
          "electrical_wire_and_connectors": "kg",
          "control_circuit_board_basic": "unit"
        },
        "recipe_run_id": "d497a1c7-20cb-45b1-911c-16169f5637a8",
        "step_index": 2,
        "energy_kwh": 0.2
      }
    ],
    "total_events_processed": 12
  },
  "orchestrator": {
    "recipe_runs": {
      "bfa7dd3c-a293-4a29-aaba-8a4aca96d994": {
        "recipe_run_id": "bfa7dd3c-a293-4a29-aaba-8a4aca96d994",
        "recipe_id": "recipe_regolith_lunar_highlands_v0",
        "target_item_id": "regolith_lunar_highlands",
        "recipe_def": {
          "id": "recipe_regolith_lunar_highlands_v0",
          "target_item_id": "regolith_lunar_highlands",
          "variant_id": null,
          "steps": [
            {
              "process_id": "regolith_mining_lunar_highlands_v0",
              "time_model": null,
              "energy_model": null,
              "inputs": [],
              "outputs": [
                {
                  "item_id": "regolith_lunar_highlands",
                  "qty": 1.0,
                  "unit": "kg",
                  "notes": null
                }
              ],
              "byproducts": [],
              "est_time_hr": null,
              "labor_hours": null,
              "machine_hours": null,
              "notes": null,
              "scale": 300.0
            }
          ],
          "inputs": [],
          "outputs": [
            {
              "item_id": "regolith_lunar_highlands",
              "qty": 1.0,
              "unit": "kg",
              "notes": null
            }
          ],
          "alternatives": [],
          "dedupe_candidate": null,
          "assumptions": null,
          "notes": "Bootstrap Highlands regolith supply via simple mining process.",
          "kind": "recipe"
        },
        "started_at": 0.0,
        "completed_steps": [
          0
        ],
        "active_steps": {},
        "scheduled_steps": {},
        "is_completed": true,
        "completed_at": 3.0
      },
      "3aa8f7fe-6d9f-4394-9762-663a935ddcbc": {
        "recipe_run_id": "3aa8f7fe-6d9f-4394-9762-663a935ddcbc",
        "recipe_id": "recipe_alumina_powder_v0",
        "target_item_id": "alumina_powder",
        "recipe_def": {
          "id": "recipe_alumina_powder_v0",
          "target_item_id": "alumina_powder",
          "variant_id": "v0",
          "steps": [
            {
              "process_id": "alumina_extraction_from_highlands_v0",
              "time_model": null,
              "energy_model": null,
              "inputs": [],
              "outputs": [
                {
                  "item_id": "alumina_powder",
                  "qty": 12.0,
                  "unit": "kg",
                  "notes": null
                },
                {
                  "item_id": "processed_tailings_v0",
                  "qty": 98.0,
                  "unit": "kg",
                  "notes": null
                }
              ],
              "byproducts": [],
              "est_time_hr": 10.0,
              "labor_hours": null,
              "machine_hours": null,
              "notes": "Extract alumina from highland regolith using HCl leaching",
              "scale": 3.0
            }
          ],
          "inputs": [
            {
              "item_id": "regolith_lunar_highlands",
              "qty": 100.0,
              "unit": "kg",
              "notes": null
            },
            {
              "item_id": "hydrochloric_acid",
              "qty": 10.0,
              "unit": "kg",
              "notes": null
            }
          ],
          "outputs": [
            {
              "item_id": "alumina_powder",
              "qty": 12.0,
              "unit": "kg",
              "notes": null
            },
            {
              "item_id": "processed_tailings_v0",
              "qty": 98.0,
              "unit": "kg",
              "notes": null
            }
          ],
          "alternatives": [],
          "dedupe_candidate": null,
          "assumptions": null,
          "notes": "Alumina extraction from lunar highland regolith. Produces 12 kg alumina per 100 kg regolith input.",
          "kind": "recipe"
        },
        "started_at": 5.0,
        "completed_steps": [
          0
        ],
        "active_steps": {},
        "scheduled_steps": {},
        "is_completed": true,
        "completed_at": 35.0
      },
      "c0e69cbe-8be1-4aca-b36e-b61aa569ab90": {
        "recipe_run_id": "c0e69cbe-8be1-4aca-b36e-b61aa569ab90",
        "recipe_id": "recipe_refractory_castable_v0",
        "target_item_id": "refractory_castable",
        "recipe_def": {
          "id": "recipe_refractory_castable_v0",
          "target_item_id": "refractory_castable",
          "variant_id": null,
          "steps": [
            {
              "process_id": "refractory_castable_mixing_v0",
              "time_model": null,
              "energy_model": null,
              "inputs": [
                {
                  "item_id": "alumina_powder",
                  "qty": 0.7,
                  "unit": "kg",
                  "notes": null
                },
                {
                  "item_id": "ceramic_binder",
                  "qty": 0.2,
                  "unit": "kg",
                  "notes": null
                },
                {
                  "item_id": "water",
                  "qty": 0.1,
                  "unit": "kg",
                  "notes": null
                }
              ],
              "outputs": [
                {
                  "item_id": "refractory_castable",
                  "qty": 1.0,
                  "unit": "kg",
                  "notes": null
                }
              ],
              "byproducts": [],
              "est_time_hr": null,
              "labor_hours": null,
              "machine_hours": null,
              "notes": null,
              "scale": 50.0
            }
          ],
          "inputs": [
            {
              "item_id": "alumina_powder",
              "qty": 0.7,
              "unit": "kg",
              "notes": null
            },
            {
              "item_id": "ceramic_binder",
              "qty": 0.2,
              "unit": "kg",
              "notes": null
            },
            {
              "item_id": "water",
              "qty": 0.1,
              "unit": "kg",
              "notes": null
            }
          ],
          "outputs": [
            {
              "item_id": "refractory_castable",
              "qty": 1.0,
              "unit": "kg",
              "notes": null
            }
          ],
          "alternatives": [],
          "dedupe_candidate": null,
          "assumptions": null,
          "notes": "Single-step recipe: mix alumina powder, ceramic binder, and water into refractory_castable.",
          "kind": "recipe"
        },
        "started_at": 45.0,
        "completed_steps": [
          0
        ],
        "active_steps": {},
        "scheduled_steps": {},
        "is_completed": true,
        "completed_at": 70.0
      },
      "d497a1c7-20cb-45b1-911c-16169f5637a8": {
        "recipe_run_id": "d497a1c7-20cb-45b1-911c-16169f5637a8",
        "recipe_id": "recipe_kiln_ceramic_v0",
        "target_item_id": "kiln_ceramic",
        "recipe_def": {
          "id": "recipe_kiln_ceramic_v0",
          "target_item_id": "kiln_ceramic",
          "variant_id": "v0",
          "steps": [
            {
              "process_id": "refractory_casting_v0",
              "time_model": null,
              "energy_model": null,
              "inputs": [
                {
                  "item_id": "refractory_castable",
                  "qty": 50.0,
                  "unit": "kg",
                  "notes": null
                }
              ],
              "outputs": [
                {
                  "item_id": "furnace_chamber_unequipped",
                  "qty": 1.0,
                  "unit": "unit",
                  "notes": null
                }
              ],
              "byproducts": [],
              "est_time_hr": 3.0,
              "labor_hours": 1.0,
              "machine_hours": 2.0,
              "notes": "Cast and cure refractory/insulated kiln shell."
            },
            {
              "process_id": "heating_element_installation_v0",
              "time_model": null,
              "energy_model": null,
              "inputs": [
                {
                  "item_id": "heating_element_resistive",
                  "qty": 1.0,
                  "unit": "unit",
                  "notes": null
                },
                {
                  "item_id": "furnace_chamber_unequipped",
                  "qty": 1.0,
                  "unit": "unit",
                  "notes": null
                }
              ],
              "outputs": [
                {
                  "item_id": "furnace_chamber_equipped",
                  "qty": 1.0,
                  "unit": "unit",
                  "notes": null
                }
              ],
              "byproducts": [],
              "est_time_hr": 1.5,
              "labor_hours": 1.5,
              "machine_hours": null,
              "notes": "Install and fixture heating elements within kiln chamber."
            },
            {
              "process_id": "electrical_assembly_basic_v0",
              "time_model": null,
              "energy_model": null,
              "inputs": [
                {
                  "item_id": "furnace_chamber_equipped",
                  "qty": 1.0,
                  "unit": "unit",
                  "notes": null
                },
                {
                  "item_id": "electrical_wire_and_connectors",
                  "qty": 2.0,
                  "unit": "kg",
                  "notes": null
                },
                {
                  "item_id": "control_circuit_board_basic",
                  "qty": 1.0,
                  "unit": "unit",
                  "notes": null
                }
              ],
              "outputs": [
                {
                  "item_id": "kiln_ceramic",
                  "qty": 1.0,
                  "unit": "unit",
                  "notes": null
                }
              ],
              "byproducts": [],
              "est_time_hr": 1.0,
              "labor_hours": 1.0,
              "machine_hours": null,
              "notes": "Wire control unit, sensors, and power connections."
            }
          ],
          "inputs": [
            {
              "item_id": "refractory_castable",
              "qty": 50.0,
              "unit": "kg",
              "notes": null
            },
            {
              "item_id": "furnace_chamber_unequipped",
              "qty": 1.0,
              "unit": "unit",
              "notes": null
            },
            {
              "item_id": "heating_element_resistive",
              "qty": 1.0,
              "unit": "unit",
              "notes": null
            },
            {
              "item_id": "electrical_wire_and_connectors",
              "qty": 2.0,
              "unit": "kg",
              "notes": null
            },
            {
              "item_id": "control_circuit_board_basic",
              "qty": 1.0,
              "unit": "unit",
              "notes": null
            }
          ],
          "outputs": [
            {
              "item_id": "kiln_ceramic",
              "qty": 1.0,
              "unit": "unit",
              "notes": null
            }
          ],
          "alternatives": [],
          "dedupe_candidate": null,
          "assumptions": "Electric heating; refractory materials available; compute imported.",
          "notes": "Ceramic kiln assembly for firing and annealing.",
          "kind": "recipe",
          "name": "Recipe for kiln_ceramic"
        },
        "started_at": 75.0,
        "completed_steps": [
          0,
          1,
          2
        ],
        "active_steps": {},
        "scheduled_steps": {},
        "is_completed": true,
        "completed_at": 78.0
      }
    }
  },
  "reservation_manager": {
    "machine_capacities": {
      "labor_bot_general_v0": 2.0,
      "assembly_station": 1.0,
      "assembly_tools_basic": 1.0,
      "refractory_installation_tools": 1.0,
      "mixer_or_blender": 1.0,
      "chemical_reactor_basic": 1.0
    },
    "reservations": [],
    "current_time": 0.0
  }
}