{
  "sim_id": "reduction_furnace_v0_v2",
  "state": {
    "sim_id": "reduction_furnace_v0_v2",
    "current_time_hours": 434.0,
    "inventory": {
      "labor_bot_general_v0": {
        "quantity": 2.0,
        "unit": "unit"
      },
      "assembly_tools_basic": {
        "quantity": 1.0,
        "unit": "unit"
      },
      "milling_machine_general_v0": {
        "quantity": 1.0,
        "unit": "unit"
      },
      "cutting_tools_general": {
        "quantity": 1.0,
        "unit": "unit"
      },
      "welding_power_supply_v0": {
        "quantity": 1.0,
        "unit": "unit"
      },
      "welding_consumables": {
        "quantity": 1.0,
        "unit": "unit"
      },
      "fixturing_workbench": {
        "quantity": 1.0,
        "unit": "unit"
      },
      "furnace_basic": {
        "quantity": 1.0,
        "unit": "unit"
      },
      "crucible_refractory": {
        "quantity": 1.0,
        "unit": "unit"
      },
      "casting_mold_set": {
        "quantity": 1.0,
        "unit": "unit"
      },
      "hot_press_v0": {
        "quantity": 1.0,
        "unit": "unit"
      },
      "sintering_furnace_v0": {
        "quantity": 1.0,
        "unit": "unit"
      },
      "dies": {
        "quantity": 1.0,
        "unit": "unit"
      },
      "rock_crusher_basic": {
        "quantity": 1.0,
        "unit": "unit"
      },
      "vibrating_screen_v0": {
        "quantity": 1.0,
        "unit": "unit"
      },
      "dust_collection_system": {
        "quantity": 1.0,
        "unit": "unit"
      },
      "ball_mill_v0": {
        "quantity": 1.0,
        "unit": "unit"
      },
      "mre_reactor_v0": {
        "quantity": 1.0,
        "unit": "unit"
      },
      "high_temperature_power_supply_v0": {
        "quantity": 1.0,
        "unit": "unit"
      },
      "electrodes": {
        "quantity": 1.0,
        "unit": "unit"
      },
      "electrical_energy": {
        "quantity": 18000.0,
        "unit": "kWh"
      },
      "regolith_coarse_fraction": {
        "quantity": 880.0,
        "unit": "kg"
      },
      "regolith_fine_fraction": {
        "quantity": 1760.0,
        "unit": "kg"
      },
      "oxygen_gas": {
        "quantity": 668.8,
        "unit": "kg"
      },
      "regolith_metal_crude": {
        "quantity": 388.20000000000005,
        "unit": "kg"
      },
      "reduction_furnace_v0": {
        "quantity": 1.0,
        "unit": "unit"
      }
    },
    "active_processes": [],
    "machines_built": [],
    "machines_in_use": {},
    "total_imports": {
      "labor_bot_general_v0": {
        "quantity": 2.0,
        "unit": "unit"
      },
      "assembly_tools_basic": {
        "quantity": 1.0,
        "unit": "unit"
      },
      "milling_machine_general_v0": {
        "quantity": 1.0,
        "unit": "unit"
      },
      "cutting_tools_general": {
        "quantity": 1.0,
        "unit": "unit"
      },
      "welding_power_supply_v0": {
        "quantity": 1.0,
        "unit": "unit"
      },
      "welding_consumables": {
        "quantity": 1.0,
        "unit": "unit"
      },
      "fixturing_workbench": {
        "quantity": 1.0,
        "unit": "unit"
      },
      "furnace_basic": {
        "quantity": 1.0,
        "unit": "unit"
      },
      "crucible_refractory": {
        "quantity": 1.0,
        "unit": "unit"
      },
      "casting_mold_set": {
        "quantity": 1.0,
        "unit": "unit"
      },
      "hot_press_v0": {
        "quantity": 1.0,
        "unit": "unit"
      },
      "sintering_furnace_v0": {
        "quantity": 1.0,
        "unit": "unit"
      },
      "dies": {
        "quantity": 1.0,
        "unit": "unit"
      },
      "rock_crusher_basic": {
        "quantity": 1.0,
        "unit": "unit"
      },
      "vibrating_screen_v0": {
        "quantity": 1.0,
        "unit": "unit"
      },
      "dust_collection_system": {
        "quantity": 1.0,
        "unit": "unit"
      },
      "ball_mill_v0": {
        "quantity": 1.0,
        "unit": "unit"
      },
      "mre_reactor_v0": {
        "quantity": 1.0,
        "unit": "unit"
      },
      "high_temperature_power_supply_v0": {
        "quantity": 1.0,
        "unit": "unit"
      },
      "electrodes": {
        "quantity": 1.0,
        "unit": "unit"
      },
      "electrical_energy": {
        "quantity": 18000.0,
        "unit": "kWh"
      },
      "refractory_castable": {
        "quantity": 100.0,
        "unit": "kg"
      },
      "thermal_insulation_high_temp": {
        "quantity": 25.0,
        "unit": "kg"
      },
      "gas_blower_basic": {
        "quantity": 1.0,
        "unit": "unit"
      },
      "fastener_kit_medium": {
        "quantity": 2.0,
        "unit": "unit"
      },
      "ceramic_insulators": {
        "quantity": 1.0,
        "unit": "unit"
      },
      "fastener_kit_small": {
        "quantity": 0.5,
        "unit": "kg"
      },
      "thermal_insulation_regolith_based_v0": {
        "quantity": 120.0,
        "unit": "kg"
      },
      "heating_element_set_high_temp": {
        "quantity": 1.0,
        "unit": "unit"
      },
      "offgas_manifold": {
        "quantity": 1.0,
        "unit": "unit"
      },
      "cooling_loop_basic": {
        "quantity": 1.0,
        "unit": "unit"
      },
      "temperature_sensing": {
        "quantity": 1.0,
        "unit": "unit"
      },
      "sensor_suite_general": {
        "quantity": 1.0,
        "unit": "unit"
      },
      "control_compute_module_imported": {
        "quantity": 1.0,
        "unit": "unit"
      }
    },
    "provenance": {
      "labor_bot_general_v0": {
        "in_situ_kg": 0.0,
        "imported_kg": 240.0,
        "unknown_kg": 0.0
      },
      "assembly_tools_basic": {
        "in_situ_kg": 0.0,
        "imported_kg": 50.0,
        "unknown_kg": 0.0
      },
      "milling_machine_general_v0": {
        "in_situ_kg": 0.0,
        "imported_kg": 600.0,
        "unknown_kg": 0.0
      },
      "cutting_tools_general": {
        "in_situ_kg": 0.0,
        "imported_kg": 30.0,
        "unknown_kg": 0.0
      },
      "welding_power_supply_v0": {
        "in_situ_kg": 0.0,
        "imported_kg": 180.0,
        "unknown_kg": 0.0
      },
      "welding_consumables": {
        "in_situ_kg": 0.0,
        "imported_kg": 25.0,
        "unknown_kg": 0.0
      },
      "fixturing_workbench": {
        "in_situ_kg": 0.0,
        "imported_kg": 150.0,
        "unknown_kg": 0.0
      },
      "furnace_basic": {
        "in_situ_kg": 0.0,
        "imported_kg": 300.0,
        "unknown_kg": 0.0
      },
      "crucible_refractory": {
        "in_situ_kg": 0.0,
        "imported_kg": 15.0,
        "unknown_kg": 0.0
      },
      "casting_mold_set": {
        "in_situ_kg": 0.0,
        "imported_kg": 100.0,
        "unknown_kg": 0.0
      },
      "hot_press_v0": {
        "in_situ_kg": 0.0,
        "imported_kg": 950.0,
        "unknown_kg": 0.0
      },
      "sintering_furnace_v0": {
        "in_situ_kg": 0.0,
        "imported_kg": 1067.0,
        "unknown_kg": 0.0
      },
      "dies": {
        "in_situ_kg": 0.0,
        "imported_kg": 40.0,
        "unknown_kg": 0.0
      },
      "rock_crusher_basic": {
        "in_situ_kg": 0.0,
        "imported_kg": 500.0,
        "unknown_kg": 0.0
      },
      "vibrating_screen_v0": {
        "in_situ_kg": 0.0,
        "imported_kg": 180.0,
        "unknown_kg": 0.0
      },
      "dust_collection_system": {
        "in_situ_kg": 0.0,
        "imported_kg": 200.0,
        "unknown_kg": 0.0
      },
      "ball_mill_v0": {
        "in_situ_kg": 0.0,
        "imported_kg": 1100.0,
        "unknown_kg": 0.0
      },
      "mre_reactor_v0": {
        "in_situ_kg": 0.0,
        "imported_kg": 1600.0,
        "unknown_kg": 0.0
      },
      "high_temperature_power_supply_v0": {
        "in_situ_kg": 0.0,
        "imported_kg": 320.0,
        "unknown_kg": 0.0
      },
      "electrodes": {
        "in_situ_kg": 0.0,
        "imported_kg": 15.0,
        "unknown_kg": 0.0
      },
      "regolith_lunar_mare": {
        "in_situ_kg": 0.0,
        "imported_kg": 0.0,
        "unknown_kg": 0.0
      },
      "regolith_coarse_fraction": {
        "in_situ_kg": 880.0,
        "imported_kg": 0.0,
        "unknown_kg": 0.0
      },
      "regolith_fine_fraction": {
        "in_situ_kg": 1760.0,
        "imported_kg": 0.0,
        "unknown_kg": 0.0
      },
      "regolith_powder": {
        "in_situ_kg": 88.0,
        "imported_kg": 0.0,
        "unknown_kg": 0.0
      },
      "oxygen_gas": {
        "in_situ_kg": 668.8,
        "imported_kg": 0.0,
        "unknown_kg": 0.0
      },
      "regolith_metal_crude": {
        "in_situ_kg": 388.19999999999993,
        "imported_kg": 0.0,
        "unknown_kg": 0.0
      },
      "refractory_castable": {
        "in_situ_kg": 0.0,
        "imported_kg": 0.0,
        "unknown_kg": 0.0
      },
      "thermal_insulation_high_temp": {
        "in_situ_kg": 0.0,
        "imported_kg": 0.0,
        "unknown_kg": 0.0
      },
      "cast_metal_parts": {
        "in_situ_kg": 32.99999999999999,
        "imported_kg": 0.0,
        "unknown_kg": 0.0
      },
      "welded_assemblies": {
        "in_situ_kg": 5.0,
        "imported_kg": 0.0,
        "unknown_kg": 0.0
      },
      "sintered_shapes": {
        "in_situ_kg": 0.0,
        "imported_kg": 5.0,
        "unknown_kg": 0.0
      },
      "reduction_furnace_shell": {
        "in_situ_kg": 0.0,
        "imported_kg": 0.0,
        "unknown_kg": 0.0
      },
      "gas_blower_basic": {
        "in_situ_kg": 0.0,
        "imported_kg": 0.0,
        "unknown_kg": 0.0
      },
      "fastener_kit_medium": {
        "in_situ_kg": 0.0,
        "imported_kg": 0.0,
        "unknown_kg": 0.0
      },
      "machined_part_raw": {
        "in_situ_kg": 7.000000000000007,
        "imported_kg": 0.0,
        "unknown_kg": 0.0
      },
      "gas_handling_system": {
        "in_situ_kg": 29.65909090909092,
        "imported_kg": 6.3409090909090935,
        "unknown_kg": 0.0
      },
      "ceramic_insulators": {
        "in_situ_kg": 0.0,
        "imported_kg": 0.0,
        "unknown_kg": 0.0
      },
      "fastener_kit_small": {
        "in_situ_kg": 0.0,
        "imported_kg": 0.0,
        "unknown_kg": 0.0
      },
      "power_bus_high_current": {
        "in_situ_kg": 3.271028037383175,
        "imported_kg": 0.2289719626168223,
        "unknown_kg": 0.0
      },
      "thermal_insulation_regolith_based_v0": {
        "in_situ_kg": 0.0,
        "imported_kg": 0.0,
        "unknown_kg": 0.0
      },
      "insulation_pack_high_temp": {
        "in_situ_kg": 0.0,
        "imported_kg": 0.0,
        "unknown_kg": 0.0
      },
      "heating_element_set_high_temp": {
        "in_situ_kg": 0.0,
        "imported_kg": 0.0,
        "unknown_kg": 0.0
      },
      "offgas_manifold": {
        "in_situ_kg": 0.0,
        "imported_kg": 0.0,
        "unknown_kg": 0.0
      },
      "cooling_loop_basic": {
        "in_situ_kg": 0.0,
        "imported_kg": 0.0,
        "unknown_kg": 0.0
      },
      "temperature_sensing": {
        "in_situ_kg": 0.0,
        "imported_kg": 0.0,
        "unknown_kg": 0.0
      },
      "sensor_suite_general": {
        "in_situ_kg": 0.0,
        "imported_kg": 0.0,
        "unknown_kg": 0.0
      },
      "control_compute_module_imported": {
        "in_situ_kg": 0.0,
        "imported_kg": 0.0,
        "unknown_kg": 0.0
      },
      "reduction_furnace_v0": {
        "in_situ_kg": 537.0698810535259,
        "imported_kg": 482.43011894647407,
        "unknown_kg": 0.0
      }
    },
    "complexity_scores": {
      "regolith_lunar_mare": 1,
      "regolith_coarse_fraction": 2,
      "regolith_fine_fraction": 2,
      "regolith_powder": 3,
      "oxygen_gas": 4,
      "regolith_metal_crude": 4,
      "cast_metal_parts": 5,
      "welded_assemblies": 7,
      "sintered_shapes": 2,
      "reduction_furnace_shell": 7,
      "machined_part_raw": 6,
      "gas_handling_system": 7,
      "power_bus_high_current": 7,
      "insulation_pack_high_temp": 2,
      "reduction_furnace_v0": 7
    },
    "total_energy_kwh": 21074.710526315786
  },
  "scheduler": {
    "current_time": 434.0,
    "event_queue": [],
    "active_processes": {},
    "completed_processes": [
      {
        "process_run_id": "05cb1e76-a889-4d3e-bbe4-b51e5fd5951c",
        "process_id": "regolith_mining_simple_v0",
        "start_time": 0.0,
        "duration_hours": 44.0,
        "end_time": 44.0,
        "scale": 1.0,
        "inputs_consumed": {},
        "outputs_pending": {
          "regolith_lunar_mare": 4400.0
        },
        "outputs_pending_units": {
          "regolith_lunar_mare": "kg"
        },
        "machines_reserved": {
          "labor_bot_general_v0": 1.0
        },
        "provenance_consumed_kg": {
          "in_situ_kg": 0.0,
          "imported_kg": 0.0,
          "unknown_kg": 0.0
        },
        "inputs_consumed_units": {},
        "recipe_run_id": "5f373a7c-c943-4d78-9029-5a9fb1f3f212",
        "step_index": 0,
        "energy_kwh": 220.0
      },
      {
        "process_run_id": "052aa749-a215-4acd-9018-ddd24d3be1e2",
        "process_id": "regolith_screening_sieving_v0",
        "start_time": 44.0,
        "duration_hours": 1.0,
        "end_time": 45.0,
        "scale": 1.0,
        "inputs_consumed": {
          "regolith_lunar_mare": 4400.0
        },
        "outputs_pending": {
          "regolith_coarse_fraction": 2640.0,
          "regolith_fine_fraction": 1760.0
        },
        "outputs_pending_units": {
          "regolith_coarse_fraction": "kg",
          "regolith_fine_fraction": "kg"
        },
        "machines_reserved": {
          "labor_bot_general_v0": 1.0,
          "vibrating_screen_v0": 1.0,
          "dust_collection_system": 1.0
        },
        "provenance_consumed_kg": {
          "in_situ_kg": 4400.0,
          "imported_kg": 0.0,
          "unknown_kg": 0.0
        },
        "inputs_consumed_units": {
          "regolith_lunar_mare": "kg"
        },
        "recipe_run_id": "5f373a7c-c943-4d78-9029-5a9fb1f3f212",
        "step_index": 1,
        "energy_kwh": 220.0
      },
      {
        "process_run_id": "1127988b-cf67-45e8-a281-83310b987c9a",
        "process_id": "regolith_crushing_grinding_v0",
        "start_time": 45.0,
        "duration_hours": 1.0,
        "end_time": 46.0,
        "scale": 1.0,
        "inputs_consumed": {
          "regolith_coarse_fraction": 1760.0
        },
        "outputs_pending": {
          "regolith_powder": 1672.0
        },
        "outputs_pending_units": {
          "regolith_powder": "kg"
        },
        "machines_reserved": {
          "labor_bot_general_v0": 1.0,
          "rock_crusher_basic": 1.0,
          "ball_mill_v0": 1.0,
          "dust_collection_system": 1.0
        },
        "provenance_consumed_kg": {
          "in_situ_kg": 1760.0,
          "imported_kg": 0.0,
          "unknown_kg": 0.0
        },
        "inputs_consumed_units": {
          "regolith_coarse_fraction": "kg"
        },
        "recipe_run_id": "5f373a7c-c943-4d78-9029-5a9fb1f3f212",
        "step_index": 2,
        "energy_kwh": 528.0
      },
      {
        "process_run_id": "0ba1e1de-80fc-45e7-994c-8bffac2c6f0c",
        "process_id": "oxygen_extraction_molten_regolith_electrolysis_v0",
        "start_time": 46.0,
        "duration_hours": 132.0,
        "end_time": 178.0,
        "scale": 1.0,
        "inputs_consumed": {
          "regolith_powder": 1672.0
        },
        "outputs_pending": {
          "oxygen_gas": 668.8,
          "regolith_metal_crude": 1003.2
        },
        "outputs_pending_units": {
          "oxygen_gas": "kg",
          "regolith_metal_crude": "kg"
        },
        "machines_reserved": {
          "labor_bot_general_v0": 1.0,
          "mre_reactor_v0": 1.0,
          "high_temperature_power_supply_v0": 1.0,
          "electrodes": 1.0
        },
        "provenance_consumed_kg": {
          "in_situ_kg": 1672.0,
          "imported_kg": 0.0,
          "unknown_kg": 0.0
        },
        "inputs_consumed_units": {
          "regolith_powder": "kg"
        },
        "recipe_run_id": "5f373a7c-c943-4d78-9029-5a9fb1f3f212",
        "step_index": 3,
        "energy_kwh": 16719.999999999996
      },
      {
        "process_run_id": "207f834d-0bc0-4344-a36f-14c2ccbae098",
        "process_id": "metal_casting_basic_v0",
        "start_time": 320.0,
        "duration_hours": 1.5,
        "end_time": 321.5,
        "scale": 1.0,
        "inputs_consumed": {
          "regolith_metal_crude": 400.0
        },
        "outputs_pending": {
          "cast_metal_parts": 380.0
        },
        "outputs_pending_units": {
          "cast_metal_parts": "kg"
        },
        "machines_reserved": {
          "labor_bot_general_v0": 1.0,
          "crucible_refractory": 1.0,
          "furnace_basic": 1.0,
          "casting_mold_set": 1.0
        },
        "provenance_consumed_kg": {
          "in_situ_kg": 400.0,
          "imported_kg": 0.0,
          "unknown_kg": 0.0
        },
        "inputs_consumed_units": {
          "regolith_metal_crude": "kg"
        },
        "recipe_run_id": "3d965928-8151-4ed6-8a8a-16141fb00171",
        "step_index": 0,
        "energy_kwh": 1400.0
      },
      {
        "process_run_id": "b283d9e3-f22a-4acb-80b8-6413a61bd2bc",
        "process_id": "welding_brazing_basic_v0",
        "start_time": 321.5,
        "duration_hours": 1.0,
        "end_time": 322.5,
        "scale": 1.0,
        "inputs_consumed": {
          "cast_metal_parts": 380.0
        },
        "outputs_pending": {
          "welded_assemblies": 375.0
        },
        "outputs_pending_units": {
          "welded_assemblies": "kg"
        },
        "machines_reserved": {
          "labor_bot_general_v0": 1.0,
          "welding_power_supply_v0": 1.0,
          "welding_consumables": 1.0,
          "fixturing_workbench": 1.0
        },
        "provenance_consumed_kg": {
          "in_situ_kg": 380.0,
          "imported_kg": 0.0,
          "unknown_kg": 0.0
        },
        "inputs_consumed_units": {
          "cast_metal_parts": "kg"
        },
        "recipe_run_id": "3d965928-8151-4ed6-8a8a-16141fb00171",
        "step_index": 1,
        "energy_kwh": 760.0
      },
      {
        "process_run_id": "3eb3492b-cb0e-4244-92d6-3619ed68808a",
        "process_id": "sintering_and_hot_pressing_v0",
        "start_time": 322.5,
        "duration_hours": 2.0,
        "end_time": 324.5,
        "scale": 1.0,
        "inputs_consumed": {
          "refractory_castable": 100.0
        },
        "outputs_pending": {
          "sintered_shapes": 95.0
        },
        "outputs_pending_units": {
          "sintered_shapes": "kg"
        },
        "machines_reserved": {
          "labor_bot_general_v0": 1.0,
          "hot_press_v0": 1.0,
          "sintering_furnace_v0": 1.0,
          "dies": 1.0
        },
        "provenance_consumed_kg": {
          "in_situ_kg": 0.0,
          "imported_kg": 100.0,
          "unknown_kg": 0.0
        },
        "inputs_consumed_units": {
          "refractory_castable": "kg"
        },
        "recipe_run_id": "3d965928-8151-4ed6-8a8a-16141fb00171",
        "step_index": 2,
        "energy_kwh": 190.0
      },
      {
        "process_run_id": "835bd417-af52-4006-997d-e743df551c20",
        "process_id": "assembly_basic_v0",
        "start_time": 324.5,
        "duration_hours": 1.0,
        "end_time": 325.5,
        "scale": 1.0,
        "inputs_consumed": {
          "welded_assemblies": 375.0,
          "sintered_shapes": 95.0,
          "thermal_insulation_high_temp": 25.0
        },
        "outputs_pending": {
          "reduction_furnace_shell": 1.0
        },
        "outputs_pending_units": {
          "reduction_furnace_shell": "unit"
        },
        "machines_reserved": {
          "labor_bot_general_v0": 1.0,
          "assembly_tools_basic": 1.0
        },
        "provenance_consumed_kg": {
          "in_situ_kg": 375.0,
          "imported_kg": 120.0,
          "unknown_kg": 0.0
        },
        "inputs_consumed_units": {
          "welded_assemblies": "kg",
          "sintered_shapes": "kg",
          "thermal_insulation_high_temp": "kg"
        },
        "recipe_run_id": "3d965928-8151-4ed6-8a8a-16141fb00171",
        "step_index": 3,
        "energy_kwh": 0.0
      },
      {
        "process_run_id": "5ada77e4-13f7-4a47-926b-1856e5c14bc5",
        "process_id": "metal_casting_basic_v0",
        "start_time": 335.0,
        "duration_hours": 1.5,
        "end_time": 336.5,
        "scale": 1.0,
        "inputs_consumed": {
          "regolith_metal_crude": 160.0
        },
        "outputs_pending": {
          "cast_metal_parts": 150.0
        },
        "outputs_pending_units": {
          "cast_metal_parts": "kg"
        },
        "machines_reserved": {
          "labor_bot_general_v0": 1.0,
          "crucible_refractory": 1.0,
          "furnace_basic": 1.0,
          "casting_mold_set": 1.0
        },
        "provenance_consumed_kg": {
          "in_situ_kg": 160.0,
          "imported_kg": 0.0,
          "unknown_kg": 0.0
        },
        "inputs_consumed_units": {
          "regolith_metal_crude": "kg"
        },
        "recipe_run_id": "4a0edfbf-454e-4dee-a784-c55c963723b7",
        "step_index": 0,
        "energy_kwh": 552.6315789473684
      },
      {
        "process_run_id": "255d84d7-e070-4ac5-84d8-656f3125d4fb",
        "process_id": "machining_finish_basic_v0",
        "start_time": 336.5,
        "duration_hours": 43.5043504350435,
        "end_time": 380.0043504350435,
        "scale": 1.0,
        "inputs_consumed": {
          "cast_metal_parts": 150.0
        },
        "outputs_pending": {
          "machined_part_raw": 145.0
        },
        "outputs_pending_units": {
          "machined_part_raw": "kg"
        },
        "machines_reserved": {
          "labor_bot_general_v0": 1.0,
          "milling_machine_general_v0": 1.0,
          "cutting_tools_general": 1.0
        },
        "provenance_consumed_kg": {
          "in_situ_kg": 150.0,
          "imported_kg": 0.0,
          "unknown_kg": 0.0
        },
        "inputs_consumed_units": {
          "cast_metal_parts": "kg"
        },
        "recipe_run_id": "4a0edfbf-454e-4dee-a784-c55c963723b7",
        "step_index": 1,
        "energy_kwh": 217.5
      },
      {
        "process_run_id": "addf410e-7c78-4961-8abc-fef9944b89c3",
        "process_id": "welding_brazing_basic_v0",
        "start_time": 380.0043504350435,
        "duration_hours": 1.0,
        "end_time": 381.0043504350435,
        "scale": 1.0,
        "inputs_consumed": {
          "machined_part_raw": 145.0
        },
        "outputs_pending": {
          "welded_assemblies": 145.0
        },
        "outputs_pending_units": {
          "welded_assemblies": "kg"
        },
        "machines_reserved": {
          "labor_bot_general_v0": 1.0,
          "welding_power_supply_v0": 1.0,
          "welding_consumables": 1.0,
          "fixturing_workbench": 1.0
        },
        "provenance_consumed_kg": {
          "in_situ_kg": 145.0,
          "imported_kg": 0.0,
          "unknown_kg": 0.0
        },
        "inputs_consumed_units": {
          "machined_part_raw": "kg"
        },
        "recipe_run_id": "4a0edfbf-454e-4dee-a784-c55c963723b7",
        "step_index": 2,
        "energy_kwh": 0.0
      },
      {
        "process_run_id": "1485b36d-bb5b-4263-b2e8-8acaa4381934",
        "process_id": "assembly_basic_v0",
        "start_time": 381.0043504350435,
        "duration_hours": 1.0,
        "end_time": 382.0043504350435,
        "scale": 1.0,
        "inputs_consumed": {
          "welded_assemblies": 145.0,
          "gas_blower_basic": 1.0,
          "fastener_kit_medium": 1.0
        },
        "outputs_pending": {
          "gas_handling_system": 1.0
        },
        "outputs_pending_units": {
          "gas_handling_system": "unit"
        },
        "machines_reserved": {
          "labor_bot_general_v0": 1.0,
          "assembly_tools_basic": 1.0
        },
        "provenance_consumed_kg": {
          "in_situ_kg": 145.0,
          "imported_kg": 31.0,
          "unknown_kg": 0.0
        },
        "inputs_consumed_units": {
          "welded_assemblies": "kg",
          "gas_blower_basic": "unit",
          "fastener_kit_medium": "unit"
        },
        "recipe_run_id": "4a0edfbf-454e-4dee-a784-c55c963723b7",
        "step_index": 3,
        "energy_kwh": 0.0
      },
      {
        "process_run_id": "52b4f6bd-c68c-4802-96bd-34a4214c2d32",
        "process_id": "metal_casting_basic_v0",
        "start_time": 395.0,
        "duration_hours": 1.5,
        "end_time": 396.5,
        "scale": 1.0,
        "inputs_consumed": {
          "regolith_metal_crude": 55.0
        },
        "outputs_pending": {
          "cast_metal_parts": 52.0
        },
        "outputs_pending_units": {
          "cast_metal_parts": "kg"
        },
        "machines_reserved": {
          "labor_bot_general_v0": 1.0,
          "crucible_refractory": 1.0,
          "furnace_basic": 1.0,
          "casting_mold_set": 1.0
        },
        "provenance_consumed_kg": {
          "in_situ_kg": 55.0,
          "imported_kg": 0.0,
          "unknown_kg": 0.0
        },
        "inputs_consumed_units": {
          "regolith_metal_crude": "kg"
        },
        "recipe_run_id": "9be18e29-ac3e-4202-b946-d61edff371e4",
        "step_index": 0,
        "energy_kwh": 191.57894736842104
      },
      {
        "process_run_id": "f2820311-14b0-429d-96ac-33de2bedbe9d",
        "process_id": "machining_finish_basic_v0",
        "start_time": 396.5,
        "duration_hours": 15.001500150015001,
        "end_time": 411.501500150015,
        "scale": 1.0,
        "inputs_consumed": {
          "cast_metal_parts": 52.0
        },
        "outputs_pending": {
          "machined_part_raw": 50.0
        },
        "outputs_pending_units": {
          "machined_part_raw": "kg"
        },
        "machines_reserved": {
          "labor_bot_general_v0": 1.0,
          "milling_machine_general_v0": 1.0,
          "cutting_tools_general": 1.0
        },
        "provenance_consumed_kg": {
          "in_situ_kg": 52.00000000000001,
          "imported_kg": 0.0,
          "unknown_kg": 0.0
        },
        "inputs_consumed_units": {
          "cast_metal_parts": "kg"
        },
        "recipe_run_id": "9be18e29-ac3e-4202-b946-d61edff371e4",
        "step_index": 1,
        "energy_kwh": 75.0
      },
      {
        "process_run_id": "5c494b34-30f1-4ae9-9d01-6e42d4956a55",
        "process_id": "assembly_basic_v0",
        "start_time": 411.501500150015,
        "duration_hours": 1.0,
        "end_time": 412.501500150015,
        "scale": 1.0,
        "inputs_consumed": {
          "machined_part_raw": 50.0,
          "ceramic_insulators": 3.0,
          "fastener_kit_small": 0.5
        },
        "outputs_pending": {
          "power_bus_high_current": 50.0
        },
        "outputs_pending_units": {
          "power_bus_high_current": "kg"
        },
        "machines_reserved": {
          "labor_bot_general_v0": 1.0,
          "assembly_tools_basic": 1.0
        },
        "provenance_consumed_kg": {
          "in_situ_kg": 50.0,
          "imported_kg": 3.5,
          "unknown_kg": 0.0
        },
        "inputs_consumed_units": {
          "machined_part_raw": "kg",
          "ceramic_insulators": "kg",
          "fastener_kit_small": "kg"
        },
        "recipe_run_id": "9be18e29-ac3e-4202-b946-d61edff371e4",
        "step_index": 2,
        "energy_kwh": 0.0
      },
      {
        "process_run_id": "c869c38b-1c89-4994-852a-e5198a6dd502",
        "process_id": "assembly_basic_v0",
        "start_time": 425.0,
        "duration_hours": 1.0,
        "end_time": 426.0,
        "scale": 1.0,
        "inputs_consumed": {
          "thermal_insulation_regolith_based_v0": 120.0
        },
        "outputs_pending": {
          "insulation_pack_high_temp": 1.0
        },
        "outputs_pending_units": {
          "insulation_pack_high_temp": "unit"
        },
        "machines_reserved": {
          "labor_bot_general_v0": 1.0,
          "assembly_tools_basic": 1.0
        },
        "provenance_consumed_kg": {
          "in_situ_kg": 0.0,
          "imported_kg": 120.0,
          "unknown_kg": 0.0
        },
        "inputs_consumed_units": {
          "thermal_insulation_regolith_based_v0": "kg"
        },
        "recipe_run_id": "77b08492-8076-4e9b-a3c9-3df3108e0ba2",
        "step_index": 0,
        "energy_kwh": 0.0
      },
      {
        "process_run_id": "f464015e-f000-4c50-8aca-b14b8fc0175e",
        "process_id": "assembly_basic_v0",
        "start_time": 431.0,
        "duration_hours": 1.0,
        "end_time": 432.0,
        "scale": 1.0,
        "inputs_consumed": {
          "reduction_furnace_shell": 1.0,
          "heating_element_set_high_temp": 1.0,
          "insulation_pack_high_temp": 1.0,
          "gas_handling_system": 1.0,
          "offgas_manifold": 1.0,
          "cooling_loop_basic": 1.0,
          "power_bus_high_current": 1.0,
          "temperature_sensing": 1.0,
          "sensor_suite_general": 1.0,
          "control_compute_module_imported": 1.0,
          "fastener_kit_medium": 1.0
        },
        "outputs_pending": {
          "reduction_furnace_v0": 1.0
        },
        "outputs_pending_units": {
          "reduction_furnace_v0": "unit"
        },
        "machines_reserved": {
          "labor_bot_general_v0": 1.0,
          "assembly_tools_basic": 1.0
        },
        "provenance_consumed_kg": {
          "in_situ_kg": 537.0698810535259,
          "imported_kg": 482.43011894647407,
          "unknown_kg": 0.0
        },
        "inputs_consumed_units": {
          "reduction_furnace_shell": "unit",
          "heating_element_set_high_temp": "unit",
          "insulation_pack_high_temp": "unit",
          "gas_handling_system": "unit",
          "offgas_manifold": "unit",
          "cooling_loop_basic": "unit",
          "power_bus_high_current": "unit",
          "temperature_sensing": "unit",
          "sensor_suite_general": "unit",
          "control_compute_module_imported": "unit",
          "fastener_kit_medium": "unit"
        },
        "recipe_run_id": "246aae61-e1fc-45d4-977e-bf1d7d4b3e48",
        "step_index": 0,
        "energy_kwh": 0.0
      }
    ],
    "total_events_processed": 34
  },
  "orchestrator": {
    "recipe_runs": {
      "5f373a7c-c943-4d78-9029-5a9fb1f3f212": {
        "recipe_run_id": "5f373a7c-c943-4d78-9029-5a9fb1f3f212",
        "recipe_id": "recipe_regolith_metal_crude_v0",
        "target_item_id": "regolith_metal_crude",
        "recipe_def": {
          "id": "recipe_regolith_metal_crude_v0",
          "target_item_id": "regolith_metal_crude",
          "variant_id": "v0",
          "steps": [
            {
              "process_id": "regolith_mining_simple_v0",
              "time_model": null,
              "energy_model": null,
              "inputs": [],
              "outputs": [
                {
                  "item_id": "regolith_lunar_mare",
                  "qty": 100.0,
                  "unit": "kg",
                  "notes": null
                }
              ],
              "byproducts": [],
              "est_time_hr": 1.0,
              "labor_hours": null,
              "machine_hours": 1.0,
              "notes": "Mine mare regolith from surface",
              "scale": 44.0
            },
            {
              "process_id": "regolith_screening_sieving_v0",
              "time_model": null,
              "energy_model": null,
              "inputs": [
                {
                  "item_id": "regolith_lunar_mare",
                  "qty": 100.0,
                  "unit": "kg",
                  "notes": null
                }
              ],
              "outputs": [
                {
                  "item_id": "regolith_coarse_fraction",
                  "qty": 60.0,
                  "unit": "kg",
                  "notes": null
                },
                {
                  "item_id": "regolith_fine_fraction",
                  "qty": 40.0,
                  "unit": "kg",
                  "notes": null
                }
              ],
              "byproducts": [],
              "est_time_hr": 0.5,
              "labor_hours": null,
              "machine_hours": 0.5,
              "notes": "Screen and separate size fractions",
              "scale": 44.0
            },
            {
              "process_id": "regolith_crushing_grinding_v0",
              "time_model": null,
              "energy_model": null,
              "inputs": [
                {
                  "item_id": "regolith_coarse_fraction",
                  "qty": 40.0,
                  "unit": "kg",
                  "notes": null
                }
              ],
              "outputs": [
                {
                  "item_id": "regolith_powder",
                  "qty": 38.0,
                  "unit": "kg",
                  "notes": null
                }
              ],
              "byproducts": [],
              "est_time_hr": 1.5,
              "labor_hours": null,
              "machine_hours": 1.5,
              "notes": "Crush and grind coarse regolith to powder",
              "scale": 44.0
            },
            {
              "process_id": "oxygen_extraction_molten_regolith_electrolysis_v0",
              "time_model": null,
              "energy_model": null,
              "inputs": [
                {
                  "item_id": "regolith_powder",
                  "qty": 38.0,
                  "unit": "kg",
                  "notes": null
                }
              ],
              "outputs": [
                {
                  "item_id": "oxygen_gas",
                  "qty": 15.2,
                  "unit": "kg",
                  "notes": null
                },
                {
                  "item_id": "regolith_metal_crude",
                  "qty": 22.8,
                  "unit": "kg",
                  "notes": null
                }
              ],
              "byproducts": [],
              "est_time_hr": 4.0,
              "labor_hours": null,
              "machine_hours": 4.0,
              "notes": "Extract oxygen and produce metal byproduct via MRE",
              "scale": 44.0
            }
          ],
          "inputs": [
            {
              "item_id": "regolith_lunar_mare",
              "qty": 100.0,
              "unit": "kg",
              "notes": null
            }
          ],
          "outputs": [
            {
              "item_id": "regolith_metal_crude",
              "qty": 22.8,
              "unit": "kg",
              "notes": null
            },
            {
              "item_id": "oxygen_gas",
              "qty": 15.2,
              "unit": "kg",
              "notes": null
            },
            {
              "item_id": "regolith_fine_fraction",
              "qty": 40.0,
              "unit": "kg",
              "notes": null
            },
            {
              "item_id": "regolith_coarse_fraction",
              "qty": 20.0,
              "unit": "kg",
              "notes": null
            }
          ],
          "alternatives": [],
          "dedupe_candidate": null,
          "assumptions": "Co-product metal alloy from MRE; refining not modeled.",
          "notes": "Coarse route; add refining/separation later.",
          "kind": "recipe"
        },
        "started_at": 0.0,
        "completed_steps": [
          0,
          1,
          2,
          3
        ],
        "active_steps": {},
        "scheduled_steps": {},
        "is_completed": true,
        "completed_at": 178.0
      },
      "3d965928-8151-4ed6-8a8a-16141fb00171": {
        "recipe_run_id": "3d965928-8151-4ed6-8a8a-16141fb00171",
        "recipe_id": "recipe_reduction_furnace_shell_v0",
        "target_item_id": "reduction_furnace_shell",
        "recipe_def": {
          "id": "recipe_reduction_furnace_shell_v0",
          "target_item_id": "reduction_furnace_shell",
          "variant_id": "v0",
          "steps": [
            {
              "process_id": "metal_casting_basic_v0",
              "time_model": null,
              "energy_model": null,
              "inputs": [
                {
                  "item_id": "regolith_metal_crude",
                  "qty": 400.0,
                  "unit": "kg",
                  "notes": null
                }
              ],
              "outputs": [
                {
                  "item_id": "cast_metal_parts",
                  "qty": 380.0,
                  "unit": "kg",
                  "notes": null
                }
              ],
              "byproducts": [],
              "est_time_hr": 6.0,
              "labor_hours": null,
              "machine_hours": 6.0,
              "notes": "Cast outer shell sections"
            },
            {
              "process_id": "welding_brazing_basic_v0",
              "time_model": null,
              "energy_model": null,
              "inputs": [
                {
                  "item_id": "cast_metal_parts",
                  "qty": 380.0,
                  "unit": "kg",
                  "notes": null
                }
              ],
              "outputs": [
                {
                  "item_id": "welded_assemblies",
                  "qty": 375.0,
                  "unit": "kg",
                  "notes": null
                }
              ],
              "byproducts": [],
              "est_time_hr": 4.0,
              "labor_hours": 4.0,
              "machine_hours": 4.0,
              "notes": "Weld shell sections together"
            },
            {
              "process_id": "sintering_and_hot_pressing_v0",
              "time_model": null,
              "energy_model": null,
              "inputs": [
                {
                  "item_id": "refractory_castable",
                  "qty": 100.0,
                  "unit": "kg",
                  "notes": null
                }
              ],
              "outputs": [
                {
                  "item_id": "sintered_shapes",
                  "qty": 95.0,
                  "unit": "kg",
                  "notes": null
                }
              ],
              "byproducts": [],
              "est_time_hr": 3.5,
              "labor_hours": null,
              "machine_hours": 3.5,
              "notes": "Apply sintered refractory lining"
            },
            {
              "process_id": "assembly_basic_v0",
              "time_model": null,
              "energy_model": null,
              "inputs": [
                {
                  "item_id": "welded_assemblies",
                  "qty": 375.0,
                  "unit": "kg",
                  "notes": null
                },
                {
                  "item_id": "sintered_shapes",
                  "qty": 95.0,
                  "unit": "kg",
                  "notes": null
                },
                {
                  "item_id": "thermal_insulation_high_temp",
                  "qty": 25.0,
                  "unit": "kg",
                  "notes": null
                }
              ],
              "outputs": [
                {
                  "item_id": "reduction_furnace_shell",
                  "qty": 1.0,
                  "unit": "unit",
                  "notes": null
                }
              ],
              "byproducts": [],
              "est_time_hr": 1.5,
              "labor_hours": 1.5,
              "machine_hours": null,
              "notes": "Final assembly with insulation"
            }
          ],
          "inputs": [
            {
              "item_id": "regolith_metal_crude",
              "qty": 400.0,
              "unit": "kg",
              "notes": "Steel for outer shell casting"
            },
            {
              "item_id": "refractory_castable",
              "qty": 100.0,
              "unit": "kg",
              "notes": "Refractory material for lining"
            },
            {
              "item_id": "thermal_insulation_high_temp",
              "qty": 25.0,
              "unit": "kg",
              "notes": "Thermal insulation"
            }
          ],
          "outputs": [
            {
              "item_id": "reduction_furnace_shell",
              "qty": 1.0,
              "unit": "unit",
              "notes": null
            }
          ],
          "alternatives": [],
          "dedupe_candidate": null,
          "assumptions": "520 kg reduction furnace shell with refractory lining.",
          "notes": "Four-step recipe for reduction furnace shell."
        },
        "started_at": 320.0,
        "completed_steps": [
          0,
          1,
          2,
          3
        ],
        "active_steps": {},
        "scheduled_steps": {},
        "is_completed": true,
        "completed_at": 325.5
      },
      "4a0edfbf-454e-4dee-a784-c55c963723b7": {
        "recipe_run_id": "4a0edfbf-454e-4dee-a784-c55c963723b7",
        "recipe_id": "recipe_gas_handling_system_v0",
        "target_item_id": "gas_handling_system",
        "recipe_def": {
          "id": "recipe_gas_handling_system_v0",
          "target_item_id": "gas_handling_system",
          "variant_id": "v0",
          "steps": [
            {
              "process_id": "metal_casting_basic_v0",
              "time_model": null,
              "energy_model": null,
              "inputs": [
                {
                  "item_id": "regolith_metal_crude",
                  "qty": 160.0,
                  "unit": "kg",
                  "notes": null
                }
              ],
              "outputs": [
                {
                  "item_id": "cast_metal_parts",
                  "qty": 150.0,
                  "unit": "kg",
                  "notes": null
                }
              ],
              "byproducts": [],
              "est_time_hr": 3.0,
              "labor_hours": null,
              "machine_hours": 3.0,
              "notes": "Cast pipe sections, valve bodies, blower housing"
            },
            {
              "process_id": "machining_finish_basic_v0",
              "time_model": null,
              "energy_model": null,
              "inputs": [
                {
                  "item_id": "cast_metal_parts",
                  "qty": 150.0,
                  "unit": "kg",
                  "notes": null
                }
              ],
              "outputs": [
                {
                  "item_id": "machined_part_raw",
                  "qty": 145.0,
                  "unit": "kg",
                  "notes": null
                }
              ],
              "byproducts": [],
              "est_time_hr": 2.0,
              "labor_hours": null,
              "machine_hours": 2.0,
              "notes": "Machine valve seats and flange faces"
            },
            {
              "process_id": "welding_brazing_basic_v0",
              "time_model": null,
              "energy_model": null,
              "inputs": [
                {
                  "item_id": "machined_part_raw",
                  "qty": 145.0,
                  "unit": "kg",
                  "notes": null
                }
              ],
              "outputs": [
                {
                  "item_id": "welded_assemblies",
                  "qty": 145.0,
                  "unit": "kg",
                  "notes": null
                }
              ],
              "byproducts": [],
              "est_time_hr": 3.0,
              "labor_hours": 3.0,
              "machine_hours": 3.0,
              "notes": "Weld pipe sections and connections"
            },
            {
              "process_id": "assembly_basic_v0",
              "time_model": null,
              "energy_model": null,
              "inputs": [
                {
                  "item_id": "welded_assemblies",
                  "qty": 145.0,
                  "unit": "kg",
                  "notes": null
                },
                {
                  "item_id": "gas_blower_basic",
                  "qty": 1.0,
                  "unit": "unit",
                  "notes": null
                },
                {
                  "item_id": "fastener_kit_medium",
                  "qty": 1.0,
                  "unit": "unit",
                  "notes": null
                }
              ],
              "outputs": [
                {
                  "item_id": "gas_handling_system",
                  "qty": 1.0,
                  "unit": "unit",
                  "notes": null
                }
              ],
              "byproducts": [],
              "est_time_hr": 2.0,
              "labor_hours": 2.0,
              "machine_hours": null,
              "notes": "Assemble system with valves and blower"
            }
          ],
          "inputs": [
            {
              "item_id": "regolith_metal_crude",
              "qty": 160.0,
              "unit": "kg",
              "notes": null
            },
            {
              "item_id": "gas_blower_basic",
              "qty": 1.0,
              "unit": "unit",
              "notes": null
            },
            {
              "item_id": "fastener_kit_medium",
              "qty": 1.0,
              "unit": "unit",
              "notes": null
            }
          ],
          "outputs": [
            {
              "item_id": "gas_handling_system",
              "qty": 1.0,
              "unit": "unit",
              "notes": null
            }
          ],
          "alternatives": [],
          "dedupe_candidate": null,
          "assumptions": "140 kg gas handling system for reduction furnace gas loop.",
          "notes": "Four-step recipe for gas handling system."
        },
        "started_at": 335.0,
        "completed_steps": [
          0,
          1,
          2,
          3
        ],
        "active_steps": {},
        "scheduled_steps": {},
        "is_completed": true,
        "completed_at": 382.0043504350435
      },
      "9be18e29-ac3e-4202-b946-d61edff371e4": {
        "recipe_run_id": "9be18e29-ac3e-4202-b946-d61edff371e4",
        "recipe_id": "recipe_power_bus_high_current_v0",
        "target_item_id": "power_bus_high_current",
        "recipe_def": {
          "id": "recipe_power_bus_high_current_v0",
          "target_item_id": "power_bus_high_current",
          "variant_id": "v0",
          "steps": [
            {
              "process_id": "metal_casting_basic_v0",
              "time_model": null,
              "energy_model": null,
              "inputs": [
                {
                  "item_id": "regolith_metal_crude",
                  "qty": 55.0,
                  "unit": "kg",
                  "notes": null
                }
              ],
              "outputs": [
                {
                  "item_id": "cast_metal_parts",
                  "qty": 52.0,
                  "unit": "kg",
                  "notes": null
                }
              ],
              "byproducts": [],
              "est_time_hr": 1.5,
              "labor_hours": null,
              "machine_hours": 1.5,
              "notes": "Cast copper bus bar blanks"
            },
            {
              "process_id": "machining_finish_basic_v0",
              "time_model": null,
              "energy_model": null,
              "inputs": [
                {
                  "item_id": "cast_metal_parts",
                  "qty": 52.0,
                  "unit": "kg",
                  "notes": null
                }
              ],
              "outputs": [
                {
                  "item_id": "machined_part_raw",
                  "qty": 50.0,
                  "unit": "kg",
                  "notes": null
                }
              ],
              "byproducts": [],
              "est_time_hr": 1.5,
              "labor_hours": null,
              "machine_hours": 1.5,
              "notes": "Machine connection holes and mounting surfaces"
            },
            {
              "process_id": "assembly_basic_v0",
              "time_model": null,
              "energy_model": null,
              "inputs": [
                {
                  "item_id": "machined_part_raw",
                  "qty": 50.0,
                  "unit": "kg",
                  "notes": null
                },
                {
                  "item_id": "ceramic_insulators",
                  "qty": 3.0,
                  "unit": "kg",
                  "notes": null
                },
                {
                  "item_id": "fastener_kit_small",
                  "qty": 0.5,
                  "unit": "kg",
                  "notes": null
                }
              ],
              "outputs": [
                {
                  "item_id": "power_bus_high_current",
                  "qty": 50.0,
                  "unit": "kg",
                  "notes": null
                }
              ],
              "byproducts": [],
              "est_time_hr": 1.0,
              "labor_hours": 1.0,
              "machine_hours": null,
              "notes": "Assemble bus with insulators and connectors"
            }
          ],
          "inputs": [
            {
              "item_id": "regolith_metal_crude",
              "qty": 55.0,
              "unit": "kg",
              "notes": null
            },
            {
              "item_id": "ceramic_insulators",
              "qty": 3.0,
              "unit": "kg",
              "notes": null
            },
            {
              "item_id": "fastener_kit_small",
              "qty": 0.5,
              "unit": "kg",
              "notes": null
            }
          ],
          "outputs": [
            {
              "item_id": "power_bus_high_current",
              "qty": 50.0,
              "unit": "kg",
              "notes": null
            }
          ],
          "alternatives": [],
          "dedupe_candidate": null,
          "assumptions": "50 kg high-current bus for furnace/reactor power distribution.",
          "notes": "Three-step recipe for high-current power bus."
        },
        "started_at": 395.0,
        "completed_steps": [
          0,
          1,
          2
        ],
        "active_steps": {},
        "scheduled_steps": {},
        "is_completed": true,
        "completed_at": 412.501500150015
      },
      "77b08492-8076-4e9b-a3c9-3df3108e0ba2": {
        "recipe_run_id": "77b08492-8076-4e9b-a3c9-3df3108e0ba2",
        "recipe_id": "recipe_insulation_pack_high_temp_regolith_v0",
        "target_item_id": "insulation_pack_high_temp",
        "recipe_def": {
          "id": "recipe_insulation_pack_high_temp_regolith_v0",
          "target_item_id": "insulation_pack_high_temp",
          "variant_id": "regolith_v0",
          "steps": [
            {
              "process_id": "assembly_basic_v0",
              "time_model": null,
              "energy_model": null,
              "inputs": [
                {
                  "item_id": "thermal_insulation_regolith_based_v0",
                  "qty": 120.0,
                  "unit": "kg",
                  "notes": null
                }
              ],
              "outputs": [
                {
                  "item_id": "insulation_pack_high_temp",
                  "qty": 1.0,
                  "unit": "unit",
                  "notes": null
                }
              ],
              "byproducts": [],
              "est_time_hr": 6.0,
              "labor_hours": 1.0,
              "machine_hours": 5.0,
              "notes": "Form regolith-based insulation into panels/blankets and kit into a high-temp pack."
            }
          ],
          "inputs": [
            {
              "item_id": "thermal_insulation_regolith_based_v0",
              "qty": 120.0,
              "unit": "kg",
              "notes": null
            }
          ],
          "outputs": [
            {
              "item_id": "insulation_pack_high_temp",
              "qty": 1.0,
              "unit": "unit",
              "notes": null
            }
          ],
          "alternatives": [],
          "dedupe_candidate": null,
          "assumptions": "Regolith-based insulation can be formed into high-temperature panels with adequate thermal performance.",
          "notes": "Local alternative to ceramic fiber-based insulation pack using regolith-derived insulation.",
          "kind": "recipe",
          "name": "High-temp insulation pack from regolith-based insulation"
        },
        "started_at": 425.0,
        "completed_steps": [
          0
        ],
        "active_steps": {},
        "scheduled_steps": {},
        "is_completed": true,
        "completed_at": 426.0
      },
      "246aae61-e1fc-45d4-977e-bf1d7d4b3e48": {
        "recipe_run_id": "246aae61-e1fc-45d4-977e-bf1d7d4b3e48",
        "recipe_id": "recipe_machine_reduction_furnace_v0",
        "target_item_id": "reduction_furnace_v0",
        "recipe_def": {
          "id": "recipe_machine_reduction_furnace_v0",
          "target_item_id": "reduction_furnace_v0",
          "variant_id": "v0",
          "steps": [
            {
              "process_id": "assembly_basic_v0",
              "time_model": null,
              "energy_model": null,
              "inputs": [
                {
                  "item_id": "reduction_furnace_shell",
                  "qty": 1.0,
                  "unit": "unit",
                  "notes": null
                },
                {
                  "item_id": "heating_element_set_high_temp",
                  "qty": 1.0,
                  "unit": "unit",
                  "notes": null
                },
                {
                  "item_id": "insulation_pack_high_temp",
                  "qty": 1.0,
                  "unit": "unit",
                  "notes": null
                },
                {
                  "item_id": "gas_handling_system",
                  "qty": 1.0,
                  "unit": "unit",
                  "notes": null
                },
                {
                  "item_id": "offgas_manifold",
                  "qty": 1.0,
                  "unit": "unit",
                  "notes": null
                },
                {
                  "item_id": "cooling_loop_basic",
                  "qty": 1.0,
                  "unit": "unit",
                  "notes": null
                },
                {
                  "item_id": "power_bus_high_current",
                  "qty": 1.0,
                  "unit": "unit",
                  "notes": null
                },
                {
                  "item_id": "temperature_sensing",
                  "qty": 1.0,
                  "unit": "unit",
                  "notes": null
                },
                {
                  "item_id": "sensor_suite_general",
                  "qty": 1.0,
                  "unit": "unit",
                  "notes": null
                },
                {
                  "item_id": "control_compute_module_imported",
                  "qty": 1.0,
                  "unit": "unit",
                  "notes": null
                },
                {
                  "item_id": "fastener_kit_medium",
                  "qty": 1.0,
                  "unit": "unit",
                  "notes": null
                }
              ],
              "outputs": [
                {
                  "item_id": "reduction_furnace_v0",
                  "qty": 1.0,
                  "unit": "unit",
                  "notes": null
                }
              ],
              "byproducts": [],
              "est_time_hr": 2.5,
              "labor_hours": 2.5,
              "machine_hours": null,
              "notes": null
            }
          ],
          "inputs": [
            {
              "item_id": "reduction_furnace_shell",
              "qty": 1.0,
              "unit": "unit",
              "notes": null
            },
            {
              "item_id": "heating_element_set_high_temp",
              "qty": 1.0,
              "unit": "unit",
              "notes": null
            },
            {
              "item_id": "insulation_pack_high_temp",
              "qty": 1.0,
              "unit": "unit",
              "notes": null
            },
            {
              "item_id": "gas_handling_system",
              "qty": 1.0,
              "unit": "unit",
              "notes": null
            },
            {
              "item_id": "offgas_manifold",
              "qty": 1.0,
              "unit": "unit",
              "notes": null
            },
            {
              "item_id": "cooling_loop_basic",
              "qty": 1.0,
              "unit": "unit",
              "notes": null
            },
            {
              "item_id": "power_bus_high_current",
              "qty": 1.0,
              "unit": "unit",
              "notes": null
            },
            {
              "item_id": "temperature_sensing",
              "qty": 1.0,
              "unit": "unit",
              "notes": null
            },
            {
              "item_id": "sensor_suite_general",
              "qty": 1.0,
              "unit": "unit",
              "notes": null
            },
            {
              "item_id": "control_compute_module_imported",
              "qty": 1.0,
              "unit": "unit",
              "notes": null
            },
            {
              "item_id": "fastener_kit_medium",
              "qty": 1.0,
              "unit": "unit",
              "notes": null
            }
          ],
          "outputs": [
            {
              "item_id": "reduction_furnace_v0",
              "qty": 1.0,
              "unit": "unit",
              "notes": null
            }
          ],
          "alternatives": [],
          "dedupe_candidate": null,
          "assumptions": "Assemble per BOM; parts produced via part-level routes.",
          "notes": "Coarse assembly route; add detailed steps later."
        },
        "started_at": 431.0,
        "completed_steps": [
          0
        ],
        "active_steps": {},
        "scheduled_steps": {},
        "is_completed": true,
        "completed_at": 432.0
      }
    }
  },
  "reservation_manager": {
    "machine_capacities": {
      "labor_bot_general_v0": 2.0,
      "assembly_tools_basic": 1.0,
      "milling_machine_general_v0": 1.0,
      "cutting_tools_general": 1.0,
      "welding_power_supply_v0": 1.0,
      "welding_consumables": 1.0,
      "fixturing_workbench": 1.0,
      "furnace_basic": 1.0,
      "crucible_refractory": 1.0,
      "casting_mold_set": 1.0,
      "hot_press_v0": 1.0,
      "sintering_furnace_v0": 1.0,
      "dies": 1.0,
      "rock_crusher_basic": 1.0,
      "vibrating_screen_v0": 1.0,
      "dust_collection_system": 1.0,
      "ball_mill_v0": 1.0,
      "mre_reactor_v0": 1.0,
      "high_temperature_power_supply_v0": 1.0,
      "electrodes": 1.0,
      "temperature_sensing": 1.0,
      "control_compute_module_imported": 1.0
    },
    "reservations": [],
    "current_time": 0.0
  }
}