{
  "sim_id": "hand_tools_mechanical_runbook",
  "state": {
    "sim_id": "hand_tools_mechanical_runbook",
    "current_time_hours": 50.0,
    "inventory": {
      "labor_bot_general_v0": {
        "quantity": 2.0,
        "unit": "unit"
      },
      "power_hammer_or_press": {
        "quantity": 1.0,
        "unit": "unit"
      },
      "forge_or_induction_heater_v0": {
        "quantity": 1.0,
        "unit": "unit"
      },
      "anvil_or_die_set": {
        "quantity": 1.0,
        "unit": "unit"
      },
      "milling_machine_general_v0": {
        "quantity": 1.0,
        "unit": "unit"
      },
      "cutting_tools_general": {
        "quantity": 1.0,
        "unit": "unit"
      },
      "heat_treatment_furnace": {
        "quantity": 1.0,
        "unit": "unit"
      },
      "quench_tank": {
        "quantity": 1.0,
        "unit": "unit"
      },
      "precision_lathe": {
        "quantity": 1.0,
        "unit": "unit"
      },
      "milling_machine_cnc": {
        "quantity": 1.0,
        "unit": "unit"
      },
      "coordinate_measuring_machine": {
        "quantity": 1.0,
        "unit": "unit"
      },
      "precision_tooling_set": {
        "quantity": 1.0,
        "unit": "unit"
      },
      "surface_grinder": {
        "quantity": 1.0,
        "unit": "unit"
      },
      "grinding_wheels": {
        "quantity": 1.0,
        "unit": "unit"
      },
      "assembly_tools_basic": {
        "quantity": 1.0,
        "unit": "unit"
      },
      "hand_tools_basic": {
        "quantity": 1.0,
        "unit": "unit"
      },
      "hand_tools_mechanical": {
        "quantity": 1.0,
        "unit": "unit"
      },
      "rock_crusher_basic": {
        "quantity": 1.0,
        "unit": "unit"
      },
      "vibrating_screen_v0": {
        "quantity": 1.0,
        "unit": "unit"
      },
      "dust_collection_system": {
        "quantity": 1.0,
        "unit": "unit"
      },
      "ball_mill_v0": {
        "quantity": 1.0,
        "unit": "unit"
      },
      "mre_reactor_v0": {
        "quantity": 1.0,
        "unit": "unit"
      },
      "high_temperature_power_supply_v0": {
        "quantity": 1.0,
        "unit": "unit"
      },
      "electrodes": {
        "quantity": 1.0,
        "unit": "unit"
      },
      "electrical_energy": {
        "quantity": 500.0,
        "unit": "kWh"
      },
      "regolith_coarse_fraction": {
        "quantity": 20.0,
        "unit": "kg"
      },
      "regolith_fine_fraction": {
        "quantity": 40.0,
        "unit": "kg"
      },
      "oxygen_gas": {
        "quantity": 15.2,
        "unit": "kg"
      },
      "regolith_metal_crude": {
        "quantity": 22.8,
        "unit": "kg"
      }
    },
    "active_processes": [],
    "machines_built": [],
    "machines_in_use": {},
    "total_imports": {
      "labor_bot_general_v0": {
        "quantity": 2.0,
        "unit": "unit"
      },
      "power_hammer_or_press": {
        "quantity": 1.0,
        "unit": "unit"
      },
      "forge_or_induction_heater_v0": {
        "quantity": 1.0,
        "unit": "unit"
      },
      "anvil_or_die_set": {
        "quantity": 1.0,
        "unit": "unit"
      },
      "milling_machine_general_v0": {
        "quantity": 1.0,
        "unit": "unit"
      },
      "cutting_tools_general": {
        "quantity": 1.0,
        "unit": "unit"
      },
      "heat_treatment_furnace": {
        "quantity": 1.0,
        "unit": "unit"
      },
      "quench_tank": {
        "quantity": 1.0,
        "unit": "unit"
      },
      "precision_lathe": {
        "quantity": 1.0,
        "unit": "unit"
      },
      "milling_machine_cnc": {
        "quantity": 1.0,
        "unit": "unit"
      },
      "coordinate_measuring_machine": {
        "quantity": 1.0,
        "unit": "unit"
      },
      "precision_tooling_set": {
        "quantity": 1.0,
        "unit": "unit"
      },
      "surface_grinder": {
        "quantity": 1.0,
        "unit": "unit"
      },
      "grinding_wheels": {
        "quantity": 1.0,
        "unit": "unit"
      },
      "assembly_tools_basic": {
        "quantity": 1.0,
        "unit": "unit"
      },
      "hand_tools_basic": {
        "quantity": 1.0,
        "unit": "unit"
      },
      "metal_feedstock": {
        "quantity": 16.0,
        "unit": "kg"
      },
      "fastener_kit_small": {
        "quantity": 1.0,
        "unit": "unit"
      },
      "rock_crusher_basic": {
        "quantity": 1.0,
        "unit": "unit"
      },
      "vibrating_screen_v0": {
        "quantity": 1.0,
        "unit": "unit"
      },
      "dust_collection_system": {
        "quantity": 1.0,
        "unit": "unit"
      },
      "ball_mill_v0": {
        "quantity": 1.0,
        "unit": "unit"
      },
      "mre_reactor_v0": {
        "quantity": 1.0,
        "unit": "unit"
      },
      "high_temperature_power_supply_v0": {
        "quantity": 1.0,
        "unit": "unit"
      },
      "electrodes": {
        "quantity": 1.0,
        "unit": "unit"
      },
      "electrical_energy": {
        "quantity": 500.0,
        "unit": "kWh"
      }
    },
    "provenance": {
      "labor_bot_general_v0": {
        "in_situ_kg": 0.0,
        "imported_kg": 240.0,
        "unknown_kg": 0.0
      },
      "power_hammer_or_press": {
        "in_situ_kg": 0.0,
        "imported_kg": 500.0,
        "unknown_kg": 0.0
      },
      "forge_or_induction_heater_v0": {
        "in_situ_kg": 0.0,
        "imported_kg": 1800.0,
        "unknown_kg": 0.0
      },
      "anvil_or_die_set": {
        "in_situ_kg": 0.0,
        "imported_kg": 25.0,
        "unknown_kg": 0.0
      },
      "milling_machine_general_v0": {
        "in_situ_kg": 0.0,
        "imported_kg": 600.0,
        "unknown_kg": 0.0
      },
      "cutting_tools_general": {
        "in_situ_kg": 0.0,
        "imported_kg": 30.0,
        "unknown_kg": 0.0
      },
      "heat_treatment_furnace": {
        "in_situ_kg": 0.0,
        "imported_kg": 537.0,
        "unknown_kg": 0.0
      },
      "quench_tank": {
        "in_situ_kg": 0.0,
        "imported_kg": 200.0,
        "unknown_kg": 0.0
      },
      "precision_lathe": {
        "in_situ_kg": 0.0,
        "imported_kg": 1200.0,
        "unknown_kg": 0.0
      },
      "milling_machine_cnc": {
        "in_situ_kg": 0.0,
        "imported_kg": 1200.0,
        "unknown_kg": 0.0
      },
      "coordinate_measuring_machine": {
        "in_situ_kg": 0.0,
        "imported_kg": 800.0,
        "unknown_kg": 0.0
      },
      "precision_tooling_set": {
        "in_situ_kg": 0.0,
        "imported_kg": 25.0,
        "unknown_kg": 0.0
      },
      "surface_grinder": {
        "in_situ_kg": 0.0,
        "imported_kg": 1200.0,
        "unknown_kg": 0.0
      },
      "grinding_wheels": {
        "in_situ_kg": 0.0,
        "imported_kg": 8.0,
        "unknown_kg": 0.0
      },
      "assembly_tools_basic": {
        "in_situ_kg": 0.0,
        "imported_kg": 50.0,
        "unknown_kg": 0.0
      },
      "hand_tools_basic": {
        "in_situ_kg": 0.0,
        "imported_kg": 4.1,
        "unknown_kg": 0.0
      },
      "metal_feedstock": {
        "in_situ_kg": 0.0,
        "imported_kg": 0.0,
        "unknown_kg": 0.0
      },
      "fastener_kit_small": {
        "in_situ_kg": 0.0,
        "imported_kg": 0.0,
        "unknown_kg": 0.0
      },
      "forged_steel_parts": {
        "in_situ_kg": 0.0,
        "imported_kg": 0.5,
        "unknown_kg": 0.0
      },
      "machined_steel_part_precision": {
        "in_situ_kg": 0.0,
        "imported_kg": 0.5,
        "unknown_kg": 0.0
      },
      "finished_part": {
        "in_situ_kg": 0.0,
        "imported_kg": 0.0,
        "unknown_kg": 0.0
      },
      "finished_part_deburred": {
        "in_situ_kg": 0.0,
        "imported_kg": 0.1999999999999993,
        "unknown_kg": 0.0
      },
      "assembled_equipment": {
        "in_situ_kg": 0.0,
        "imported_kg": 0.10000000000000142,
        "unknown_kg": 0.0
      },
      "hand_tools_mechanical": {
        "in_situ_kg": 0.0,
        "imported_kg": 16.0,
        "unknown_kg": 0.0
      },
      "rock_crusher_basic": {
        "in_situ_kg": 0.0,
        "imported_kg": 500.0,
        "unknown_kg": 0.0
      },
      "vibrating_screen_v0": {
        "in_situ_kg": 0.0,
        "imported_kg": 180.0,
        "unknown_kg": 0.0
      },
      "dust_collection_system": {
        "in_situ_kg": 0.0,
        "imported_kg": 200.0,
        "unknown_kg": 0.0
      },
      "ball_mill_v0": {
        "in_situ_kg": 0.0,
        "imported_kg": 1100.0,
        "unknown_kg": 0.0
      },
      "mre_reactor_v0": {
        "in_situ_kg": 0.0,
        "imported_kg": 1600.0,
        "unknown_kg": 0.0
      },
      "high_temperature_power_supply_v0": {
        "in_situ_kg": 0.0,
        "imported_kg": 320.0,
        "unknown_kg": 0.0
      },
      "electrodes": {
        "in_situ_kg": 0.0,
        "imported_kg": 15.0,
        "unknown_kg": 0.0
      },
      "regolith_lunar_mare": {
        "in_situ_kg": 0.0,
        "imported_kg": 0.0,
        "unknown_kg": 0.0
      },
      "regolith_coarse_fraction": {
        "in_situ_kg": 20.0,
        "imported_kg": 0.0,
        "unknown_kg": 0.0
      },
      "regolith_fine_fraction": {
        "in_situ_kg": 40.0,
        "imported_kg": 0.0,
        "unknown_kg": 0.0
      },
      "regolith_powder": {
        "in_situ_kg": 2.0,
        "imported_kg": 0.0,
        "unknown_kg": 0.0
      },
      "oxygen_gas": {
        "in_situ_kg": 15.2,
        "imported_kg": 0.0,
        "unknown_kg": 0.0
      },
      "regolith_metal_crude": {
        "in_situ_kg": 22.8,
        "imported_kg": 0.0,
        "unknown_kg": 0.0
      }
    },
    "complexity_scores": {
      "forged_steel_parts": 2,
      "machined_steel_part_precision": 3,
      "finished_part": 4,
      "finished_part_deburred": 5,
      "assembled_equipment": 6,
      "hand_tools_mechanical": 7,
      "regolith_lunar_mare": 1,
      "regolith_coarse_fraction": 2,
      "regolith_fine_fraction": 2,
      "regolith_powder": 3,
      "oxygen_gas": 4,
      "regolith_metal_crude": 4
    },
    "total_energy_kwh": 440.29999999999995
  },
  "scheduler": {
    "current_time": 50.0,
    "event_queue": [],
    "active_processes": {},
    "completed_processes": [
      {
        "process_run_id": "5ac12dee-ca0e-4e4b-9185-bee961291a0d",
        "process_id": "forging_basic_v0",
        "start_time": 0.0,
        "duration_hours": 1.0,
        "end_time": 1.0,
        "scale": 1.0,
        "inputs_consumed": {
          "metal_feedstock": 16.0
        },
        "outputs_pending": {
          "forged_steel_parts": 15.5
        },
        "outputs_pending_units": {
          "forged_steel_parts": "kg"
        },
        "machines_reserved": {
          "labor_bot_general_v0": 1.0,
          "forge_or_induction_heater_v0": 1.0,
          "power_hammer_or_press": 1.0,
          "anvil_or_die_set": 1.0
        },
        "provenance_consumed_kg": {
          "in_situ_kg": 0.0,
          "imported_kg": 16.0,
          "unknown_kg": 0.0
        },
        "inputs_consumed_units": {
          "metal_feedstock": "kg"
        },
        "recipe_run_id": "c6434b30-0081-47b9-9329-55a441a981c2",
        "step_index": 0,
        "energy_kwh": 0.0
      },
      {
        "process_run_id": "c79dc59f-dc56-4d39-ab41-f7a60a060d45",
        "process_id": "machining_precision_v0",
        "start_time": 1.0,
        "duration_hours": 1.0,
        "end_time": 2.0,
        "scale": 1.0,
        "inputs_consumed": {
          "forged_steel_parts": 15.5
        },
        "outputs_pending": {
          "machined_steel_part_precision": 15.0
        },
        "outputs_pending_units": {
          "machined_steel_part_precision": "kg"
        },
        "machines_reserved": {
          "labor_bot_general_v0": 1.0,
          "precision_lathe": 1.0,
          "milling_machine_cnc": 1.0,
          "surface_grinder": 1.0,
          "coordinate_measuring_machine": 1.0,
          "precision_tooling_set": 1.0
        },
        "provenance_consumed_kg": {
          "in_situ_kg": 0.0,
          "imported_kg": 15.5,
          "unknown_kg": 0.0
        },
        "inputs_consumed_units": {
          "forged_steel_parts": "kg"
        },
        "recipe_run_id": "c6434b30-0081-47b9-9329-55a441a981c2",
        "step_index": 1,
        "energy_kwh": 0.0
      },
      {
        "process_run_id": "f420c719-e5a7-40b9-9ccf-9d23149665c5",
        "process_id": "heat_treatment_basic_v0",
        "start_time": 2.0,
        "duration_hours": 3.0,
        "end_time": 5.0,
        "scale": 1.0,
        "inputs_consumed": {
          "machined_steel_part_precision": 15.0
        },
        "outputs_pending": {
          "finished_part": 15.0
        },
        "outputs_pending_units": {
          "finished_part": "kg"
        },
        "machines_reserved": {
          "labor_bot_general_v0": 1.0,
          "heat_treatment_furnace": 1.0,
          "quench_tank": 1.0
        },
        "provenance_consumed_kg": {
          "in_situ_kg": 0.0,
          "imported_kg": 15.0,
          "unknown_kg": 0.0
        },
        "inputs_consumed_units": {
          "machined_steel_part_precision": "kg"
        },
        "recipe_run_id": "c6434b30-0081-47b9-9329-55a441a981c2",
        "step_index": 2,
        "energy_kwh": 37.5
      },
      {
        "process_run_id": "df175052-5aa7-48d2-94fc-591bdfdfcc0c",
        "process_id": "surface_finishing_basic_v0",
        "start_time": 5.0,
        "duration_hours": 1.5,
        "end_time": 6.5,
        "scale": 1.0,
        "inputs_consumed": {
          "finished_part": 15.0
        },
        "outputs_pending": {
          "finished_part_deburred": 14.8
        },
        "outputs_pending_units": {
          "finished_part_deburred": "kg"
        },
        "machines_reserved": {
          "labor_bot_general_v0": 1.0,
          "surface_grinder": 1.0,
          "hand_tools_basic": 1.0
        },
        "provenance_consumed_kg": {
          "in_situ_kg": 0.0,
          "imported_kg": 15.0,
          "unknown_kg": 0.0
        },
        "inputs_consumed_units": {
          "finished_part": "kg"
        },
        "recipe_run_id": "c6434b30-0081-47b9-9329-55a441a981c2",
        "step_index": 3,
        "energy_kwh": 0.8
      },
      {
        "process_run_id": "5b34df88-9df3-4a9f-8bfa-70371bfb92cb",
        "process_id": "assembly_basic_v0",
        "start_time": 6.5,
        "duration_hours": 1.0,
        "end_time": 7.5,
        "scale": 1.0,
        "inputs_consumed": {
          "finished_part_deburred": 14.8,
          "fastener_kit_small": 1.0
        },
        "outputs_pending": {
          "assembled_equipment": 16.0
        },
        "outputs_pending_units": {
          "assembled_equipment": "kg"
        },
        "machines_reserved": {
          "labor_bot_general_v0": 1.0,
          "assembly_tools_basic": 1.0
        },
        "provenance_consumed_kg": {
          "in_situ_kg": 0.0,
          "imported_kg": 16.1,
          "unknown_kg": 0.0
        },
        "inputs_consumed_units": {
          "finished_part_deburred": "kg",
          "fastener_kit_small": "unit"
        },
        "recipe_run_id": "c6434b30-0081-47b9-9329-55a441a981c2",
        "step_index": 4,
        "energy_kwh": 0.0
      },
      {
        "process_run_id": "6a89ff89-27e0-4e6e-a8db-e8ed57e7d199",
        "process_id": "inspection_basic_v0",
        "start_time": 7.5,
        "duration_hours": 1.0,
        "end_time": 8.5,
        "scale": 1.0,
        "inputs_consumed": {
          "assembled_equipment": 16.0
        },
        "outputs_pending": {
          "hand_tools_mechanical": 1.0
        },
        "outputs_pending_units": {
          "hand_tools_mechanical": "unit"
        },
        "machines_reserved": {
          "labor_bot_general_v0": 1.0
        },
        "provenance_consumed_kg": {
          "in_situ_kg": 0.0,
          "imported_kg": 16.0,
          "unknown_kg": 0.0
        },
        "inputs_consumed_units": {
          "assembled_equipment": "kg"
        },
        "recipe_run_id": "c6434b30-0081-47b9-9329-55a441a981c2",
        "step_index": 5,
        "energy_kwh": 0.0
      },
      {
        "process_run_id": "7a153870-3b49-48ac-a654-79d69b5b2285",
        "process_id": "regolith_mining_simple_v0",
        "start_time": 40.0,
        "duration_hours": 1.0,
        "end_time": 41.0,
        "scale": 1.0,
        "inputs_consumed": {},
        "outputs_pending": {
          "regolith_lunar_mare": 100.0
        },
        "outputs_pending_units": {
          "regolith_lunar_mare": "kg"
        },
        "machines_reserved": {
          "labor_bot_general_v0": 1.0
        },
        "provenance_consumed_kg": {
          "in_situ_kg": 0.0,
          "imported_kg": 0.0,
          "unknown_kg": 0.0
        },
        "inputs_consumed_units": {},
        "recipe_run_id": "094365fd-7963-4842-b954-9fa8274df851",
        "step_index": 0,
        "energy_kwh": 5.0
      },
      {
        "process_run_id": "2717d6cd-f3fc-4174-bf52-0b62ec110101",
        "process_id": "regolith_screening_sieving_v0",
        "start_time": 41.0,
        "duration_hours": 1.0,
        "end_time": 42.0,
        "scale": 1.0,
        "inputs_consumed": {
          "regolith_lunar_mare": 100.0
        },
        "outputs_pending": {
          "regolith_coarse_fraction": 60.0,
          "regolith_fine_fraction": 40.0
        },
        "outputs_pending_units": {
          "regolith_coarse_fraction": "kg",
          "regolith_fine_fraction": "kg"
        },
        "machines_reserved": {
          "labor_bot_general_v0": 1.0,
          "vibrating_screen_v0": 1.0,
          "dust_collection_system": 1.0
        },
        "provenance_consumed_kg": {
          "in_situ_kg": 100.0,
          "imported_kg": 0.0,
          "unknown_kg": 0.0
        },
        "inputs_consumed_units": {
          "regolith_lunar_mare": "kg"
        },
        "recipe_run_id": "094365fd-7963-4842-b954-9fa8274df851",
        "step_index": 1,
        "energy_kwh": 5.0
      },
      {
        "process_run_id": "d10eba1a-90b7-4b27-9b15-ff63b75469da",
        "process_id": "regolith_crushing_grinding_v0",
        "start_time": 42.0,
        "duration_hours": 1.0,
        "end_time": 43.0,
        "scale": 1.0,
        "inputs_consumed": {
          "regolith_coarse_fraction": 40.0
        },
        "outputs_pending": {
          "regolith_powder": 38.0
        },
        "outputs_pending_units": {
          "regolith_powder": "kg"
        },
        "machines_reserved": {
          "labor_bot_general_v0": 1.0,
          "rock_crusher_basic": 1.0,
          "ball_mill_v0": 1.0,
          "dust_collection_system": 1.0
        },
        "provenance_consumed_kg": {
          "in_situ_kg": 40.0,
          "imported_kg": 0.0,
          "unknown_kg": 0.0
        },
        "inputs_consumed_units": {
          "regolith_coarse_fraction": "kg"
        },
        "recipe_run_id": "094365fd-7963-4842-b954-9fa8274df851",
        "step_index": 2,
        "energy_kwh": 12.0
      },
      {
        "process_run_id": "56657493-65a4-4890-abd6-7d44210a004b",
        "process_id": "oxygen_extraction_molten_regolith_electrolysis_v0",
        "start_time": 43.0,
        "duration_hours": 3.0,
        "end_time": 46.0,
        "scale": 1.0,
        "inputs_consumed": {
          "regolith_powder": 38.0
        },
        "outputs_pending": {
          "oxygen_gas": 15.2,
          "regolith_metal_crude": 22.8
        },
        "outputs_pending_units": {
          "oxygen_gas": "kg",
          "regolith_metal_crude": "kg"
        },
        "machines_reserved": {
          "labor_bot_general_v0": 1.0,
          "mre_reactor_v0": 1.0,
          "high_temperature_power_supply_v0": 1.0,
          "electrodes": 1.0
        },
        "provenance_consumed_kg": {
          "in_situ_kg": 38.0,
          "imported_kg": 0.0,
          "unknown_kg": 0.0
        },
        "inputs_consumed_units": {
          "regolith_powder": "kg"
        },
        "recipe_run_id": "094365fd-7963-4842-b954-9fa8274df851",
        "step_index": 3,
        "energy_kwh": 379.99999999999994
      }
    ],
    "total_events_processed": 20
  },
  "orchestrator": {
    "recipe_runs": {
      "c6434b30-0081-47b9-9329-55a441a981c2": {
        "recipe_run_id": "c6434b30-0081-47b9-9329-55a441a981c2",
        "recipe_id": "recipe_hand_tools_mechanical_v0",
        "target_item_id": "hand_tools_mechanical",
        "recipe_def": {
          "id": "recipe_hand_tools_mechanical_v0",
          "target_item_id": "hand_tools_mechanical",
          "variant_id": "v0",
          "steps": [
            {
              "process_id": "forging_basic_v0",
              "time_model": null,
              "energy_model": null,
              "inputs": [
                {
                  "item_id": "metal_feedstock",
                  "qty": 16.0,
                  "unit": "kg",
                  "notes": null
                }
              ],
              "outputs": [
                {
                  "item_id": "forged_steel_parts",
                  "qty": 15.5,
                  "unit": "kg",
                  "notes": null
                }
              ],
              "byproducts": [],
              "est_time_hr": 8.0,
              "labor_hours": 6.0,
              "machine_hours": 6.0,
              "notes": "Hot forge wrench bodies, plier jaws, hammer heads, and other tool blanks from steel stock"
            },
            {
              "process_id": "machining_precision_v0",
              "time_model": null,
              "energy_model": null,
              "inputs": [
                {
                  "item_id": "forged_steel_parts",
                  "qty": 15.5,
                  "unit": "kg",
                  "notes": null
                }
              ],
              "outputs": [
                {
                  "item_id": "machined_steel_part_precision",
                  "qty": 15.0,
                  "unit": "kg",
                  "notes": null
                }
              ],
              "byproducts": [],
              "est_time_hr": 12.0,
              "labor_hours": 8.0,
              "machine_hours": 12.0,
              "notes": "Machine wrench openings, socket drive squares, screwdriver tips, plier pivot holes, and file cutting edges"
            },
            {
              "process_id": "heat_treatment_basic_v0",
              "time_model": null,
              "energy_model": null,
              "inputs": [
                {
                  "item_id": "machined_steel_part_precision",
                  "qty": 15.0,
                  "unit": "kg",
                  "notes": null
                }
              ],
              "outputs": [
                {
                  "item_id": "finished_part",
                  "qty": 15.0,
                  "unit": "kg",
                  "notes": null
                }
              ],
              "byproducts": [],
              "est_time_hr": 6.0,
              "labor_hours": 2.0,
              "machine_hours": 6.0,
              "notes": "Harden and temper tool steel components (wrench jaws, screwdriver tips, socket drives, plier jaws) for wear resistance"
            },
            {
              "process_id": "surface_finishing_basic_v0",
              "time_model": null,
              "energy_model": null,
              "inputs": [
                {
                  "item_id": "finished_part",
                  "qty": 15.0,
                  "unit": "kg",
                  "notes": null
                }
              ],
              "outputs": [
                {
                  "item_id": "finished_part_deburred",
                  "qty": 14.8,
                  "unit": "kg",
                  "notes": null
                }
              ],
              "byproducts": [],
              "est_time_hr": 4.0,
              "labor_hours": 3.0,
              "machine_hours": null,
              "notes": "Polish tool surfaces, remove sharp edges, apply corrosion-resistant coating (chrome plating or phosphate coating)"
            },
            {
              "process_id": "assembly_basic_v0",
              "time_model": null,
              "energy_model": null,
              "inputs": [
                {
                  "item_id": "finished_part_deburred",
                  "qty": 14.8,
                  "unit": "kg",
                  "notes": null
                },
                {
                  "item_id": "fastener_kit_small",
                  "qty": 1.0,
                  "unit": "unit",
                  "notes": null
                }
              ],
              "outputs": [
                {
                  "item_id": "assembled_equipment",
                  "qty": 16.0,
                  "unit": "kg",
                  "notes": null
                }
              ],
              "byproducts": [],
              "est_time_hr": 3.0,
              "labor_hours": 3.0,
              "machine_hours": null,
              "notes": "Assemble multi-part tools (pliers with rivets, socket wrenches with ratchet mechanisms), install handles on screwdrivers and files"
            },
            {
              "process_id": "inspection_basic_v0",
              "time_model": null,
              "energy_model": null,
              "inputs": [
                {
                  "item_id": "assembled_equipment",
                  "qty": 16.0,
                  "unit": "kg",
                  "notes": null
                }
              ],
              "outputs": [
                {
                  "item_id": "hand_tools_mechanical",
                  "qty": 1.0,
                  "unit": "unit",
                  "notes": null
                }
              ],
              "byproducts": [],
              "est_time_hr": 1.0,
              "labor_hours": 1.0,
              "machine_hours": null,
              "notes": "Verify tool hardness, dimensional accuracy, and functional testing (wrench fit, screwdriver grip, plier action)"
            }
          ],
          "inputs": [
            {
              "item_id": "metal_feedstock",
              "qty": 16.0,
              "unit": "kg",
              "notes": null
            },
            {
              "item_id": "forged_steel_parts",
              "qty": 15.5,
              "unit": "kg",
              "notes": "Intermediate for precision machining"
            },
            {
              "item_id": "machined_steel_part_precision",
              "qty": 15.0,
              "unit": "kg",
              "notes": "Intermediate for heat treatment"
            },
            {
              "item_id": "finished_part",
              "qty": 15.0,
              "unit": "kg",
              "notes": "Intermediate for surface finishing"
            },
            {
              "item_id": "finished_part_deburred",
              "qty": 14.8,
              "unit": "kg",
              "notes": "Intermediate for final assembly"
            },
            {
              "item_id": "fastener_kit_small",
              "qty": 1.0,
              "unit": "unit",
              "notes": null
            },
            {
              "item_id": "assembled_equipment",
              "qty": 16.0,
              "unit": "kg",
              "notes": "Intermediate for inspection"
            }
          ],
          "outputs": [
            {
              "item_id": "hand_tools_mechanical",
              "qty": 1.0,
              "unit": "unit",
              "notes": null
            }
          ],
          "alternatives": [],
          "dedupe_candidate": null,
          "assumptions": "Comprehensive mechanical hand tool set for assembly, maintenance, and repair. 15 kg set includes wrenches (open-end, box-end, adjustable), socket set with ratchet, screwdrivers (flat and Phillips), pliers (slip-joint, needle-nose, locking), hammers (ball-peen, claw), Allen key set, punches, and files. Hardened steel construction. Essential for all mechanical work.",
          "notes": "Manufacturing of mechanical hand tool set. Total fabrication time ~34 hours. Multi-component production includes forging, precision machining, heat treatment for hardness (HRC 45-55 for working surfaces), surface finishing, and assembly. Critical for general workshop capability.",
          "kind": "recipe"
        },
        "started_at": 0.0,
        "completed_steps": [
          0,
          1,
          2,
          3,
          4,
          5
        ],
        "active_steps": {},
        "scheduled_steps": {},
        "is_completed": true,
        "completed_at": 8.5
      },
      "094365fd-7963-4842-b954-9fa8274df851": {
        "recipe_run_id": "094365fd-7963-4842-b954-9fa8274df851",
        "recipe_id": "recipe_regolith_metal_crude_v0",
        "target_item_id": "regolith_metal_crude",
        "recipe_def": {
          "id": "recipe_regolith_metal_crude_v0",
          "target_item_id": "regolith_metal_crude",
          "variant_id": "v0",
          "steps": [
            {
              "process_id": "regolith_mining_simple_v0",
              "time_model": null,
              "energy_model": null,
              "inputs": [],
              "outputs": [
                {
                  "item_id": "regolith_lunar_mare",
                  "qty": 100.0,
                  "unit": "kg",
                  "notes": null
                }
              ],
              "byproducts": [],
              "est_time_hr": 1.0,
              "labor_hours": null,
              "machine_hours": 1.0,
              "notes": "Mine mare regolith from surface"
            },
            {
              "process_id": "regolith_screening_sieving_v0",
              "time_model": null,
              "energy_model": null,
              "inputs": [
                {
                  "item_id": "regolith_lunar_mare",
                  "qty": 100.0,
                  "unit": "kg",
                  "notes": null
                }
              ],
              "outputs": [
                {
                  "item_id": "regolith_coarse_fraction",
                  "qty": 60.0,
                  "unit": "kg",
                  "notes": null
                },
                {
                  "item_id": "regolith_fine_fraction",
                  "qty": 40.0,
                  "unit": "kg",
                  "notes": null
                }
              ],
              "byproducts": [],
              "est_time_hr": 0.5,
              "labor_hours": null,
              "machine_hours": 0.5,
              "notes": "Screen and separate size fractions"
            },
            {
              "process_id": "regolith_crushing_grinding_v0",
              "time_model": null,
              "energy_model": null,
              "inputs": [
                {
                  "item_id": "regolith_coarse_fraction",
                  "qty": 40.0,
                  "unit": "kg",
                  "notes": null
                }
              ],
              "outputs": [
                {
                  "item_id": "regolith_powder",
                  "qty": 38.0,
                  "unit": "kg",
                  "notes": null
                }
              ],
              "byproducts": [],
              "est_time_hr": 1.5,
              "labor_hours": null,
              "machine_hours": 1.5,
              "notes": "Crush and grind coarse regolith to powder"
            },
            {
              "process_id": "oxygen_extraction_molten_regolith_electrolysis_v0",
              "time_model": null,
              "energy_model": null,
              "inputs": [
                {
                  "item_id": "regolith_powder",
                  "qty": 38.0,
                  "unit": "kg",
                  "notes": null
                }
              ],
              "outputs": [
                {
                  "item_id": "oxygen_gas",
                  "qty": 15.2,
                  "unit": "kg",
                  "notes": null
                },
                {
                  "item_id": "regolith_metal_crude",
                  "qty": 22.8,
                  "unit": "kg",
                  "notes": null
                }
              ],
              "byproducts": [],
              "est_time_hr": 4.0,
              "labor_hours": null,
              "machine_hours": 4.0,
              "notes": "Extract oxygen and produce metal byproduct via MRE"
            }
          ],
          "inputs": [
            {
              "item_id": "regolith_lunar_mare",
              "qty": 100.0,
              "unit": "kg",
              "notes": null
            }
          ],
          "outputs": [
            {
              "item_id": "regolith_metal_crude",
              "qty": 22.8,
              "unit": "kg",
              "notes": null
            },
            {
              "item_id": "oxygen_gas",
              "qty": 15.2,
              "unit": "kg",
              "notes": null
            },
            {
              "item_id": "regolith_fine_fraction",
              "qty": 40.0,
              "unit": "kg",
              "notes": null
            },
            {
              "item_id": "regolith_coarse_fraction",
              "qty": 20.0,
              "unit": "kg",
              "notes": null
            }
          ],
          "alternatives": [],
          "dedupe_candidate": null,
          "assumptions": "Co-product metal alloy from MRE; refining not modeled.",
          "notes": "Coarse route; add refining/separation later.",
          "kind": "recipe"
        },
        "started_at": 40.0,
        "completed_steps": [
          0,
          1,
          2,
          3
        ],
        "active_steps": {},
        "scheduled_steps": {},
        "is_completed": true,
        "completed_at": 46.0
      }
    }
  },
  "reservation_manager": {
    "machine_capacities": {
      "labor_bot_general_v0": 2.0,
      "power_hammer_or_press": 1.0,
      "forge_or_induction_heater_v0": 1.0,
      "anvil_or_die_set": 1.0,
      "milling_machine_general_v0": 1.0,
      "cutting_tools_general": 1.0,
      "heat_treatment_furnace": 1.0,
      "quench_tank": 1.0,
      "precision_lathe": 1.0,
      "milling_machine_cnc": 1.0,
      "coordinate_measuring_machine": 1.0,
      "precision_tooling_set": 1.0,
      "surface_grinder": 1.0,
      "grinding_wheels": 1.0,
      "assembly_tools_basic": 1.0,
      "hand_tools_basic": 1.0,
      "hand_tools_mechanical": 1.0,
      "rock_crusher_basic": 1.0,
      "vibrating_screen_v0": 1.0,
      "dust_collection_system": 1.0,
      "ball_mill_v0": 1.0,
      "mre_reactor_v0": 1.0,
      "high_temperature_power_supply_v0": 1.0,
      "electrodes": 1.0
    },
    "reservations": [],
    "current_time": 0.0
  }
}